Workbook

Sheet 1. Info & Instructions
A1: Budget Web Application — UAT Test Cases
A2: Chememan PCL (CMAN) | User Acceptance Testing (UAT) | Data & Analytics | Round 1 | FY2027
A4: Project Information
A5: Application | B5: Budget Web Application
A6: Environment | B6: https://cman-budget-web-prd.kindstone-f34836dd.southeastasia.azurecontainerapps.io/
A7: Test Phase | B7: User Acceptance Test (UAT)
A8: Departments under test | B8: Data & Analytic ; Solution Delivery
A9: Fiscal year under test | B9: FY2027 — หน้าจอแสดงเป็น `Year 2026` (ปีวางแผน) · เป็นปีเดียวที่ระบบเปิดรับข้อมูล
A10: Role — Filler (ผู้กรอกงบ) · ทั้งสองฝ่าย | B10: Pornthip (pornthipp@chememan.com)
A11: Role — Approver 1 (ผู้อนุมัติขั้นที่ 1) · ทั้งสองฝ่าย | B11: Laddawan (laddawank@chememan.com)
A12: Role — Approver 2 (ผู้อนุมัติขั้นที่ 2) | B12: Nipaporn (nipapornt@chememan.com)
A13: Role — Approver 3 (ผู้อนุมัติขั้นที่ 3) | B13: Waraporn (warapornt@chememan.com)
A14: Role — เจ้าของฝ่าย Solution Delivery ตัวจริง (ไม่ได้เป็นผู้ทดสอบเคสใดใน 54 เคส) | B14: Suchanya (suchanyay@chememan.com) — เธอเป็น “ผู้กรอกงบ (Filler)” ตัวจริงของฝ่าย Solution Delivery ในไฟล์ master `cc dept.xlsx` (10IT012000) และยังเป็นอยู่ · รอบนี้ขอ “ยืมฝ่าย” ของเธอมาทดสอบ โดยเพิ่ม Pornthip เข้าไปเป็นผู้กรอกอีกคน ไม่ได้ถอดสิทธิ์ของ Suchanya ออก รอบนี้ฝ่าย Solution Delivery ถูกส่งเข้าอนุมัติจริง (เคส UAT-36) และอนุมัติถึงขั้นที่ 1 ก่อนถูกตีกลับคืน (เคส UAT-43) ระหว่างนั้น **Suchanya แก้ไขฝ่ายตัวเองไม่ได้ชั่วคราว — ต้องแจ้งเธอล่วงหน้าก่อนเริ่มรอบ** หน้าที่ของเธอในรอบนี้คือ **ยืนยันว่างานของเธอไม่เสียหาย** — ทำ **หลังจบเคส UAT-43** (ตอนที่ฝ่ายถูกตีกลับคืน สถานะ `Rejected` ให้แก้ไขได้แล้ว) ล็อกอินตามปกติ เลือกฝ่าย Solution Delivery ปี Year 2026 แล้วยืนยัน 3 ข้อ: (1) ยังเห็นพื้นที่อัปโหลดไฟล์และปุ่มลบไฟล์ตามเดิม (2) กลับมากรอกยอดในตารางได้แล้ว (3) ตัวเลขเดิมของฝ่ายไม่เปลี่ยนไปเอง — แล้วแจ้งผลสั้น ๆ กลับให้ Test Lead (ไม่มีแถวหรือช่อง Status ของเธอเองในแท็บ “2. Test Cases”) ห้ามใช้บัญชีของเธอทดสอบเคส UAT-31 เพราะเคสนั้นต้องการคนที่ “เห็นฝ่ายได้แต่ไม่ใช่ผู้กรอก” ส่วน Suchanya เป็นผู้กรอกจริง จึงต้องเห็นปุ่มอัปโหลดและปุ่มลบ ซึ่งถูกต้องแล้ว
A15: Test Lead | B15: Data and Analytics team
A16: Test Cycle / Round | B16: UAT Round 1
... A19: Total test cases | B19: 54 เคส (UAT-01 ถึง UAT-54) · จัดกลุ่มเป็น 8 ระลอก (Wave) แต่ **ลำดับการทดสอบจริงให้ดูคอลัมน์ `ลำดับการรัน` 1 → 54** ไม่ใช่คอลัมน์ Wave · ข้อมูลจริงอยู่แถวที่ 3 ถึง 56 ของแท็บ “2. Test Cases”
A21: ข้อควรระวังก่อนเริ่มทดสอบ
A22: ข้อ 1 — UAT รอบนี้รันบน **ระบบจริง (production)** ใช้ฐานข้อมูลจริง และส่งอีเมลจริงถึงเพื่อนร่วมงานจริง ไม่มีระบบทดลองแยกต่างหาก ทุกอย่างที่กรอก ส่ง อนุมัติ หรือลบ คือข้อมูลจริงของปีงบประมาณ 2027
A23: ข้อ 2 — สถานะ `Approved` **ย้อนกลับไม่ได้ในระบบ** ต้องแก้ที่ฐานข้อมูลเท่านั้น อย่ากด Approve ขั้นที่ 3 (เคส UAT-40) จนกว่าทุกเคสที่มีเลข `ลำดับการรัน` น้อยกว่า 52 จะเสร็จครบ — UAT-40 อยู่ที่ลำดับการรันที่ 52 และเป็นเคสสุดท้ายของสายอนุมัติฝ่ายนั้น ถ้ากดก่อน เคส UAT-41 · UAT-42 (ข้อ 5) · UAT-44 · UAT-47 · UAT-52 (ข้อ 1) จะทดสอบไม่ได้อีกเลยตลอดรอบ
A24: ข้อ 3 — อายุ session ระหว่าง UAT ตั้งไว้ที่ **1 ชั่วโมง** (ค่าจริงคือ 14 ชั่วโมง และจะคืนค่าเดิมหลังจบรอบ) ถ้าระบบให้ล็อกอินใหม่ระหว่างทดสอบ ถือว่าเป็นเรื่องปกติของรอบนี้
A25: ข้อ 4 — **KNOWN ISSUE ที่ไม่ต้องแจ้งเป็น defect:** กล่อง “หมดเวลาการเข้าใช้งาน” ยังเขียนว่า 14 ชั่วโมง ทั้งที่ตั้งไว้ 1 ชั่วโมง — ตัดสินแล้วว่ายอมรับได้ (jakkaritw 2026-09-06)
A26: ข้อ 5 — **เตรียมไฟล์แนบให้ฝ่าย Solution Delivery ไว้ก่อนเริ่มรอบ อย่างน้อย 1 ไฟล์** ในโฟลเดอร์ `เอกสาร ฝ่าย/Solution Delivery/2027/` (ให้ Pornthip อัปโหลดด้วยขั้นตอนเดียวกับเคส UAT-27 ซึ่งอัปโหลดให้ฝ่าย Data & Analytic เท่านั้น ไม่มีเคสใดในรอบนี้อัปโหลดให้ฝ่าย Solution Delivery) — เคส UAT-31 ต้องมีไฟล์อยู่แล้วในโฟลเดอร์นี้ก่อนจึงจะทดสอบได้ ถ้าไม่เตรียมไว้ล่วงหน้า เคสนี้จะทำไม่ได้เมื่อถึงลำดับการรัน
A27: ข้อ 6 — **ฝ่าย Solution Delivery จะถูกล็อกชั่วคราวระหว่างรอบ (ตั้งแต่เคส UAT-36 ถึง UAT-43):** ทันทีที่ Pornthip กด Submit ฝ่ายนี้ (เคส UAT-36) คุณ Suchanya ผู้กรอกตัวจริงของฝ่าย Solution Delivery จะแก้ไขงบของฝ่ายตัวเองไม่ได้เลยจนกว่าจะถูกตีกลับ — **ต้องแจ้ง Suchanya ล่วงหน้าก่อนเริ่มรอบ** ว่าจะมีช่วงล็อกสั้น ๆ นี้ · เคส UAT-43 จะอนุมัติฝ่ายนี้ที่ขั้นที่ 1 แล้วตีกลับคืนทันทีในเคสเดียวกัน เพื่อให้เธอกลับมาแก้ไขได้ก่อนจบรอบ ไม่ต้องรอจนครบทั้ง 54 เคส
A29: วิธีใช้ไฟล์นี้ / How to use this workbook
A30: 1. ไปที่แท็บ “2. Test Cases” แล้วทดสอบ **เรียงตามคอลัมน์ `ลำดับการรัน` (Run Order) จาก 1 ถึง 54** — **ไม่ใช่เรียงตามคอลัมน์ Wave** · คอลัมน์ Wave ยังเป็นชื่อกลุ่มของเคสและใช้กรองดูได้เหมือนเดิม แต่ลำดับที่ต้องลงมือทำจริงคือคอลัมน์ `ลำดับการรัน` เพราะบางเคสต้องทำข้ามระลอก (เช่น UAT-53 และ UAT-54 อยู่ระลอก W8 แต่ต้องทำก่อนระลอก W5 · UAT-03 อยู่ระลอก W1 แต่ต้องทำหลัง UAT-32)
A31: 2. วิธีเรียง: คลิกลูกศรกรองบนหัวคอลัมน์ `ลำดับการรัน` แล้วเลือก “Sort Smallest to Largest” จากนั้นไล่ทำจากบนลงล่าง
A32: 3. ⚠ **อย่ากด `Approve` ขั้นที่ 3 ในเคส UAT-40 (ลำดับการรันที่ 52) จนกว่าทุกเคสที่มีลำดับการรันน้อยกว่า 52 จะเสร็จครบ** เพราะสถานะ `Approved` ย้อนกลับไม่ได้ ถ้ากดก่อน เคส UAT-41 · UAT-42 (ข้อ 5) · UAT-44 · UAT-47 · UAT-52 (ข้อ 1) จะทดสอบไม่ได้อีกเลยตลอดรอบ และต้องให้ทีม IT แก้ที่ฐานข้อมูลเท่านั้น
A33: 4. ทดสอบทีละเคสตาม “Test Steps” แล้วเทียบผลกับ “Expected Result”
... A49: Legend / คำอธิบายสี & สถานะ
B50: ช่องพื้นหลังสีเหลือง = ช่องที่ผู้ทดสอบดูแลระหว่างรอบทดสอบ (7 ช่อง: Actual Result, Status, Severity, Defect ID, Tester, Test Date, Remarks) · ช่อง `Tester` มีชื่อกรอกไว้ล่วงหน้าแล้วตามแผนคน (ตัวหนังสือสีม่วง) ผู้ทดสอบแก้ไขได้ถ้าคนที่ทดสอบจริงเปลี่ยนไปจากแผน ส่วนอีก 6 ช่องยังว่าง กรอกเองระหว่างทดสอบ
B51: ช่อง `PIC` เป็นช่องสีขาว แต่เป็นข้อยกเว้นเดียวที่ต้องกรอก — Test Lead กรอกก่อนเริ่มรอบ ผู้ทดสอบไม่ต้องแตะ (คนละหน้าที่กับช่อง `Tester`: `PIC` = ผู้รับผิดชอบที่ Test Lead มอบหมาย, `Tester` = คนที่ต้องลงมือทดสอบตามแผน) · ช่องสีขาวอื่นทั้งหมดคือเนื้อหาเคส ไม่ต้องแก้
B52: รูปแบบ `ชื่อ(jakkarit)` ในช่อง `Tester` (พบที่ UAT-31 และช่วงหนึ่งของ UAT-43) แปลว่า **jakkaritw เป็นคนกดจริงบนเครื่อง** โดยสวมสิทธิ์ผ่านหน้า `/sit/impersonate` เป็นคนที่ชื่ออยู่หน้าวงเล็บ — ระบบบันทึกประวัติเป็นชื่อคนที่ถูกสวมสิทธิ์เท่านั้น ไม่มีคอลัมน์เก็บชื่อผู้กดจริง
B53: คอลัมน์ `ลำดับการรัน` (Run Order) = ลำดับที่ต้องลงมือทำจริง 1 → 54 · คอลัมน์ `Wave` = ชื่อกลุ่มของเคส ใช้กรองดูเท่านั้น **ไม่ใช่ลำดับการทำ** · สองคอลัมน์นี้พิมพ์ด้วย **ตัวอักษรสีดำ ไม่ใช่สีม่วง** เพราะโปรแกรมคำนวณมาให้ ไม่ใช่ข้อความที่ AI ร่าง — **ห้ามแก้ทั้งสองคอลัมน์**
B54: Status = Pass (ผลตรงตามที่คาดหวังทุกข้อ)
B55: Status = Fail (ผลไม่ตรงอย่างน้อย 1 ข้อ — ต้องเปิดแถวใน “4. Defects” และใส่เลข Defect ID)
B56: Status = Blocked (ทดสอบไม่ได้ ติดเคสอื่นหรือข้อมูลยังไม่พร้อม) · N/A (ไม่เกี่ยวกับรอบนี้)
B57: ตัวหนังสือสีม่วง = ข้อความที่ AI ร่างไว้ ยังไม่ผ่านการตรวจจากคน — แก้ได้ถ้าไม่ตรงกับระบบจริง · ตัวหนังสือสีดำในคอลัมน์ `Wave` และ `ลำดับการรัน` = ค่าที่โปรแกรมคำนวณ ห้ามแก้
A58: Severity: Critical = ระบบใช้งานไม่ได้ / ข้อมูลผิดพลาดร้ายแรง | High = ฟังก์ชันหลักเสีย | Medium = มีทางเลี่ยง | Low = ปัญหาเล็กน้อย / UI · ชุดค่านี้ใช้เหมือนกันทั้งแท็บ “2. Test Cases” และแท็บ “4. Defects” จึงยกค่าจากแถวเคสไปใส่แถว defect ได้ตรง ๆ ไม่ต้องแปลง (ค่า `-` มีเฉพาะแท็บ “2. Test Cases” ใช้เมื่อเคสนั้นไม่ Fail)

Sheet 2. Test Cases
A1: Budget Web App — UAT Test Cases (Round 1 · FY2027 · production)
A2: Wave | B2: Run Order / ลำดับการรัน | C2: No. | D2: Test Case ID | E2: Module | F2: Department | G2: PIC | H2: Test Scenario | I2: Priority | J2: Preconditions / เงื่อนไขก่อนทดสอบ | K2: Test Steps | L2: Test Data | M2: Expected Result | N2: Actual Result | O2: Status | P2: Severity | Q2: Defect ID | R2: Tester | S2: Test Date | T2: Remarks / หมายเหตุ
A3: W1 | B3: 1 | C3: 1 | D3: UAT-01 | E3: Login / Authentication | F3: ทั้งสองฝ่าย | H3: Pornthip (ผู้กรอกงบประมาณ) ล็อกอินเข้าระบบ แล้วตรวจแถบผู้ใช้ด้านบนว่าแสดงสายงาน ชื่อฝ่าย จำนวน Cost Center จำนวน GL และ role badge ตรงกับสิทธิ์จริง รวมถึงการย่อชื่อฝ่ายเหลือ 3 ชื่อแล้วต่อท้ายด้วย +N | I3: High | J3: มีบัญชีผู้ใช้ของ Pornthip (pornthipp@chememan.com) เป็น Filler และเข้าถึง URL ของระบบ (production) ได้ · ไฟล์ master `cc dept.xlsx` กำหนดให้ Pornthip เป็นผู้กรอกของทั้งฝ่าย Data & Analytic และฝ่าย Solution Delivery และ sync เข้าระบบเรียบร้อยแล้ว · ผู้ทดสอบเตรียมรายการสิทธิ์จริงของตนเองไว้เทียบก่อนเริ่ม (ชื่อสายงาน ชื่อฝ่ายทั้งหมด และจำนวน Cost Center ต่อฝ่าย) โดยขอจากผู้ดูแลระบบ (nipapornt@chememan.com) | K3: 1. เปิด URL ของระบบ (production) ด้วยเบราว์เซอร์ Chrome 2. ล็อกอินด้วยบัญชี pornthipp@chememan.com ที่หน้าล็อกอินของ Microsoft (ถ้าเคยล็อกอินบนเครื่องนี้แล้ว ระบบอาจพาเข้าให้เองโดยไม่ถามรหัสผ่าน ถือว่าปกติ) 3. รอให้หน้าหลักแสดงผล แล้วมองที่แถบผู้ใช้ด้านบนของหน้าจอ 4. อ่านค่าทีละอย่างแล้วจดลงช่อง Actual Result: ชื่อผู้ใช้และอีเมลเต็ม · ป้ายบอกสิทธิ์ (role badge) · ชื่อสายงานหลังคำว่า `สายงาน` · ชื่อฝ่ายทุกชื่อที่แสดง · ตัวเลขจำนวนฝ่ายที่อยู่ข้างคำว่า `ฝ่าย` · ตัวเลขบนป้าย `Cost Centers` · ตัวเลขบนป้าย `GL Codes` 5. เทียบจำนวนฝ่ายและจำนวน Cost Center ที่หน้าจอแสดง กับรายการสิทธิ์จริงที่เตรียมไว้ในเงื่อนไขก่อนทดสอบ 6. นับจำนวน "ชื่อฝ่าย" ที่แถบผู้ใช้แสดงจริง แล้วดูว่ามีป้ายท้ายรายการที่ขึ้นต้นด้วยเครื่องหมาย + หรือไม่ (รูปแบบของป้ายนี้คือ `+<จำนวน> ฝ่าย` เช่น `+6 ฝ่าย`) แล้วจดทั้งจำนวนชื่อที่แสดงและข้อความบนป้ายลงช่อง Actual Result 7. ทำแบบเดียวกันกับชื่อสายงาน — นับจำนวนชื่อสายงานที่แสดง และดูว่ามีป้าย `+<จำนวน> สายงาน` ต่อท้ายหรือไม่ แล้วจดไว้ 8. คลิกลิงก์ `ออกจากระบบ` ที่มุมขวาของแถบผู้ใช้เพื่อยืนยันว่าลิงก์นี้มีอยู่จริงและกดได้ (ผลของการออกจากระบบตรวจในเคส UAT-04 เคสนี้ตรวจแค่ว่ามีลิงก์) | L3: User: Pornthip (Filler) — pornthipp@chememan.com ฝ่ายที่คาดว่าจะเห็น: Data & Analytic (Cost Center 10IT011300 และ 10IT013000) และ Solution Delivery (Cost Center 10IT012000) ปีที่หน้าจอแสดง: Year 2026 (= ปีงบประมาณ 2027) | M3: 1. เข้าสู่ระบบสำเร็จ แสดงหน้าหลักตามสิทธิ์ผู้กรอกงบประมาณ โดยไม่มีข้อความ error 2. ป้ายบอกสิทธิ์ (role badge) บนแถบผู้ใช้แสดงคำว่า `ผู้กรอกงบประมาณ` 3. แถบผู้ใช้แสดง **ชื่อสายงานจริง** ของผู้ใช้ — ถ้าขึ้นเป็นข้อความ `ไม่ระบุสายงาน` ถือว่า Fail และให้แจ้งผู้ดูแลระบบตรวจการจับคู่ Cost Center กับฝ่าย/สายงานในไฟล์ master ก่อนสรุปว่าเป็นบั๊กของแอป 4. ชื่อฝ่ายที่แสดงตรงกับฝ่ายที่ผู้ใช้ถือจริง และตัวเลขจำนวนฝ่ายข้างคำว่า `ฝ่าย` ตรงกับจำนวนจริง (Pornthip = 2 ฝ่าย คือ Data & Analytic และ Solution Delivery) 5. ป้าย `Cost Centers` แสดงจำนวน Cost Center ที่ผู้ใช้กรอกได้ **รวมทุกฝ่าย** ไม่ใช่เฉพาะฝ่ายที่เลือกอยู่ — Pornthip ต้องได้เลข 3 (Data & Analytic 2 + Solution Delivery 1) 6. ป้าย `GL Codes` แสดงจำนวนรหัส GL ที่ไม่ซ้ำกันของแถวที่มีอยู่จริงในตารางของทุก Cost Center ที่กรอกได้ จึงต้องเป็นตัวเลข ไม่ใช่ `—` และตัวเลขนี้จะเพิ่มขึ้นเมื่อเพิ่มแถวใหม่ในระลอก W2 — ให้จดตัวเลขที่เห็นวันนี้ไว้ ไม่ต้องเทียบกับรายการสิทธิ์ 7. กติกาการย่อชื่อ: แถบผู้ใช้แสดงชื่อฝ่ายได้มากที่สุด **3 ชื่อ** ที่เหลือจะยุบเป็นป้ายเดียวรูปแบบ `+<จำนวนที่เหลือ> ฝ่าย` โดยตัวเลขต้องเท่ากับจำนวนฝ่ายที่ถูกซ่อนพอดี · **สำหรับ Pornthip ที่ถือ 2 ฝ่าย ผลที่ถูกต้องคือแสดงชื่อครบทั้ง 2 ชื่อ และต้องไม่มีป้าย `+` ใด ๆ เลย** ถ้าเห็นป้าย `+` ทั้งที่มีแค่ 2 ฝ่าย ถือว่า Fail 8. กติกาเดียวกันนี้ใช้กับชื่อสายงานด้วย (ย่อที่ 3 ชื่อ แล้วต่อท้ายด้วย `+<จำนวน> สายงาน`) — ให้จดผลที่เห็นไว้ 9. มีลิงก์ `ออกจากระบบ` อยู่ที่มุมขวาของแถบผู้ใช้ และกดได้ — หมายเหตุสำคัญ — เคสนี้ครอบคลุมช่องว่าง "แถบผู้ใช้และการอ่านสิทธิ์" ซึ่งไม่เคยถูกทดสอบในรอบ SIT · ถ้าจำนวนฝ่ายหรือจำนวน Cost Center ไม่ตรงกับสิทธิ์จริง ให้เปิด Defect และแจ้งผู้ดูแลระบบตรวจไฟล์ master `cc dept.xlsx` ก่อนสรุปว่าเป็นบั๊กของแอป · ข้อ 7 และ 8 (การย่อชื่อเหลือ 3 ชื่อ + ป้าย `+N`) จะเห็นผลเป็น "ไม่มีป้าย +" เพราะผู้ทดสอบถือแค่ 2 ฝ่าย นั่นคือผลที่ถูกต้อง ไม่ใช่การทดสอบที่ล้มเหลว | N3: แถบผู้ใช้แสดง: pornthipp / pornthipp@chememan.com · role badge = ผู้กรอกงบประมาณ · สายงาน = Digital Technology · ฝ่าย 2 = Data & Analytic, Solution Delivery · 3 COST CENTERS · 8 GL CODES (จดไว้ตามข้อ 6) · ไม่มีป้าย + ต่อท้ายชื่อฝ่ายหรือสายงาน · มีลิงก์ ออกจากระบบ ที่มุมขวา (ไม่ได้กด — ผลของการออกจากระบบตรวจใน UAT-04) | O3: Pass | R3: Pornthip | S3: 46274 | T3: [AI pre-run 09/09/2026] ตรงกับ Expected ข้อ 1-9 ทุกข้อ · ข้อ 8 (กดลิงก์ออกจากระบบเพื่อยืนยันว่ากดได้) ไม่ได้กดใน pre-UAT เพราะจะทำให้ session ของการรันหลุด — ให้คนกดในรอบจริง
A4: W1 | B4: 2 | C4: 2 | D4: UAT-02 | E4: Login / Authentication | F4: ทั้งสองฝ่าย | H4: ผู้กรอกงบประมาณที่ถือ 2 ฝ่าย เปิดตัวเลือกฝ่าย: หน้าจอต้องเลือกฝ่ายแรกให้อัตโนมัติและไม่ปล่อยให้ว่าง ต้องเห็นครบทั้ง 2 ฝ่ายพร้อมช่องค้นหา กลุ่มสายงาน และจำนวน Cost Center ต่อฝ่าย และสลับฝ่ายแล้วตารางหลักเปลี่ยนตาม | I4: High | J4: ล็อกอินเป็น Pornthip (pornthipp@chememan.com) · Pornthip ถูกกำหนดให้เป็นผู้กรอกของทั้ง Data & Analytic และ Solution Delivery ในไฟล์ master `cc dept.xlsx` และ sync เข้าระบบเรียบร้อยแล้ว (ยืนยันแล้วว่าใช้งานได้จริง) — ถ้าเปิดมาแล้วยังเห็นฝ่ายเดียว ให้บันทึกสถานะ Blocked ไม่ใช่ Fail แล้วแจ้งผู้ดูแลระบบ · ปีที่เลือกบนหน้าจอ = Year 2026 (ปีงบ 2027 ซึ่งเป็นปีเดียวที่เปิดรับ) · เปิดหน้าจอด้วย URL เปล่า ๆ ไม่ต้องมีข้อความต่อท้ายหลังเครื่องหมาย ? เพราะลิงก์แบบเจาะจงฝ่ายจะทับกติกาการเลือกฝ่ายเริ่มต้น | K4: 1. ล็อกอินเป็น Pornthip แล้วมองที่แถบเครื่องมือเหนือตาราง **ก่อนคลิกอะไรทั้งสิ้น** จดว่าปุ่มเลือกฝ่ายแสดงชื่อฝ่ายใดอยู่ หรือแสดงข้อความ `— เลือกฝ่าย —` 2. จดด้วยว่าตารางหลักโหลดข้อมูลของฝ่ายนั้นขึ้นมาให้แล้วหรือยังว่างเปล่า 3. คลิกที่ปุ่มเลือกฝ่ายเพื่อเปิดรายการ 4. ตรวจว่ามีช่องค้นหาอยู่ด้านบนของรายการ (ข้อความจาง ๆ ในช่องเขียนว่า `ค้นหาฝ่าย…`) และรายการฝ่ายถูกจัดกลุ่มตามสายงาน โดยหัวข้อกลุ่มมีตัวเลขจำนวนฝ่ายในสายงานนั้นกำกับอยู่ 5. อ่านจำนวน Cost Center ที่แสดงต่อท้ายชื่อฝ่ายแต่ละฝ่าย (รูปแบบ `2 CC`) แล้วจดลงช่อง Actual Result 6. พิมพ์คำค้น `Solution` ในช่องค้นหา แล้วดูว่ารายการถูกกรองให้เหลือเฉพาะฝ่ายที่ตรงกับคำค้น 7. พิมพ์คำที่ไม่มีอยู่จริง เช่น `zzz` แล้วจดข้อความที่ระบบขึ้นเมื่อไม่พบฝ่าย 8. ลบคำค้นออก แล้วเลือกฝ่าย Solution Delivery · ดูตารางหลัก จด Cost Center และจำนวนแถวที่เห็น 9. เปิดตัวเลือกฝ่ายอีกครั้ง สลับกลับไปฝ่าย Data & Analytic แล้วดูตารางหลักอีกครั้ง จดสิ่งที่เห็น 10. เปิดตัวเลือกฝ่ายอีกครั้งแล้วกดปุ่ม Esc เพื่อปิดโดยไม่เลือกฝ่าย | L4: User: Pornthip (Filler) — pornthipp@chememan.com ฝ่ายที่คาดว่าจะเห็น 2 ฝ่าย: Data & Analytic (2 Cost Center) · Solution Delivery (1 Cost Center: 10IT012000) คำค้นที่ใช้ทดสอบช่องค้นหา: `Solution` | M4: 1. เมื่อเข้าหน้าจอครั้งแรกโดยไม่ได้ใช้ลิงก์เจาะจงฝ่าย ระบบ **เลือกฝ่ายแรกตามลำดับตัวอักษรให้อัตโนมัติ** และตารางหลักโหลดข้อมูลของฝ่ายนั้นขึ้นมาเลย — สำหรับ Pornthip คือฝ่าย `Data & Analytic` · หน้าจอต้อง **ไม่** ค้างอยู่ที่ข้อความ `— เลือกฝ่าย —` (ข้อความนี้จะขึ้นก็ต่อเมื่อผู้ใช้ไม่มีสิทธิ์ในฝ่ายใดเลย) 2. เปิดรายการแล้วเห็นครบทั้ง 2 ฝ่าย จัดกลุ่มตามสายงาน และหัวข้อกลุ่มมีตัวเลขจำนวนฝ่ายในสายงานนั้นกำกับ 3. มีช่องค้นหาที่มีข้อความจาง ๆ ว่า `ค้นหาฝ่าย…` และเมื่อพิมพ์ `Solution` รายการเหลือเฉพาะฝ่ายที่ชื่อ (หรือชื่อสายงาน) มีคำนั้นอยู่ · เมื่อพิมพ์คำที่ไม่มีอยู่จริง ระบบขึ้นข้อความ `ไม่พบฝ่ายในสิทธิ์ของคุณ` 4. แต่ละฝ่ายแสดงจำนวน Cost Center ของตนเองต่อท้ายชื่อ — `Data & Analytic` = `2 CC` · `Solution Delivery` = `1 CC` 5. เมื่อเลือกฝ่ายใดฝ่ายหนึ่ง ตารางหลักโหลดข้อมูลของฝ่ายนั้น และเมื่อสลับไปอีกฝ่าย ตารางเปลี่ยนตามทันที ต้องไม่ค้างข้อมูล Cost Center ของฝ่ายก่อนหน้า 6. กด Esc แล้วรายการฝ่ายปิดลง โดยฝ่ายที่เลือกไว้เดิมไม่เปลี่ยน — หมายเหตุสำคัญ — ฝ่าย Solution Delivery ปีงบ 2027 ยังไม่มีข้อมูลที่กรอกไว้เลย (0 แถว) ดังนั้นการที่ตารางว่างหลังสลับไปฝ่ายนั้น ถือว่าปกติ ไม่ใช่ข้อผิดพลาด · การที่ระบบเลือกฝ่ายแรกให้อัตโนมัติเป็นพฤติกรรมที่ตัดสินไว้แล้ว (2026-07-21 — เดิมเคยออกแบบให้เริ่มต้นว่าง แล้วเปลี่ยนเป็นห้ามปล่อยให้หน้าจอว่าง) จึง **ไม่ใช่ defect** · ถ้ายังเห็นฝ่ายเดียว แปลว่า master `cc dept.xlsx` ยังไม่ได้แก้หรือยัง sync ไม่ถึง ให้บันทึกเป็น Blocked แล้วแจ้งผู้ดูแลระบบ | N4: ข้อ1-2: เปิดหน้าด้วย URL เปล่า ระบบเลือก Data & Analytic ให้เองทันที ตารางโหลดแถว 10IT013000 ไม่ค้างที่ '— เลือกฝ่าย —' · ข้อ4: รายการจัดกลุ่ม 'DIGITAL TECHNOLOGY 2' ช่องค้นหา placeholder = 'ค้นหาฝ่าย…' · ข้อ5: Data & Analytic = 2 CC, Solution Delivery = 1 CC · ข้อ6: พิมพ์ Solution เหลือเฉพาะ Solution Delivery 1 CC · ข้อ7: พิมพ์ zzz ขึ้น 'ไม่พบฝ่ายในสิทธิ์ของคุณ' · ข้อ8: เลือก Solution Delivery ตารางเปลี่ยนเป็น cost center 10IT012000 (ไม่มีแถว 10IT013000 ค้าง) · ข้อ9: กลับ Data & Analytic ตารางเปลี่ยนเป็น 10IT013000 สถานะ Draft — not submitted · ข้อ10: เปิดรายการแล้วกด Esc รายการปิด ปุ่มยังเป็น Data & Analytic | O4: Pass | R4: Pornthip | S4: 46274 | T4: [AI pre-run 09/09/2026] ตรง Expected ข้อ 1-6 ทุกข้อ · ข้อสังเกต (ไม่ใช่ defect): ตารางของ Solution Delivery ไม่ได้ว่างเปล่าอย่างที่ note ของเคสคาด — แสดงแถว GL ของ 10IT012000 พร้อมยอด SAP ใช้จริง แต่ชั้น Pending เป็น 0 ทั้งหมด เพราะแถวมาจากชั้น SAP ไม่ใช่ข้อมูลที่กรอก ควรแก้ note ของเคสให้ตรง
A5: W1 | B5: 35 | C5: 3 | D5: UAT-03 | E5: Login / Authentication | F5: ทั้งสองฝ่าย | H5: Laddawan (ผู้อนุมัติขั้นที่ 1) ล็อกอินเข้าระบบ เห็นหน้าจอเดียวกับผู้ใช้ทั่วไป แถบบนแสดงชื่อสายงานจริงของเธอ ป้ายในตัวเลือกฝ่ายเป็นคำภาษาอังกฤษ `Pending` และตัวเลขงบของฝ่ายที่รออนุมัติเป็นแบบอ่านอย่างเดียว | I5: High | J5: มีบัญชีผู้ใช้ของ Laddawan (laddawank@chememan.com) ซึ่งเป็นผู้อนุมัติขั้นที่ 1 ของฝ่ายที่ทดสอบ · ปีที่หน้าจอแสดง = Year 2026 (ปีงบ 2027) · **ตามลำดับการรัน เคสนี้ทำรวดเดียวจบทั้ง 6 ข้อ** เพราะอยู่หลังเคส UAT-32 (กด Submit) แล้ว ฝ่าย Data & Analytic จึงมีงบค้างรออนุมัติอยู่ที่ขั้นที่ 1 ของ Laddawan อยู่แล้วตั้งแต่ก่อนเริ่มเคสนี้ · ถ้าเปิดตัวเลือกฝ่ายแล้วไม่มีฝ่ายใดขึ้นป้าย `Pending` เลย แปลว่าเคส UAT-32 ยังไม่เสร็จ ให้กลับไปทำ UAT-32 ให้จบก่อนแล้วค่อยกลับมาทำเคสนี้ | K5: 1. เปิด URL ของระบบด้วยเบราว์เซอร์ แล้วล็อกอินด้วยบัญชี laddawank@chememan.com ที่หน้าล็อกอินของ Microsoft 2. ตรวจแถบผู้ใช้ด้านบนว่าแสดงชื่อและอีเมลของตนเอง 3. อ่านข้อความที่อยู่หลังคำว่า `สายงาน` บนแถบผู้ใช้ แล้วจดลงช่อง Actual Result ตรงตามตัวอักษร 4. เปิดตัวเลือกฝ่าย แล้วอ่านป้ายที่ติดอยู่กับฝ่ายที่ค้างรออนุมัติ — จดข้อความที่เห็นตรงตามตัวอักษร 5. เลือกฝ่ายนั้น แล้วลองคลิกเข้าไปในช่องจำนวนเงินของตารางและลองพิมพ์ตัวเลข เพื่อดูว่าแก้ไขได้หรือไม่ 6. มองหาปุ่มดำเนินการของฝ่ายนั้นบนแถบอนุมัติ แล้วจดข้อความบนปุ่มที่เห็น (ยังไม่ต้องกดปุ่มใด ๆ) | L5: User: Laddawan (Approver 1) — laddawank@chememan.com ฝ่ายที่คาดว่าจะค้างรออนุมัติ: Data & Analytic ปีงบ 2027 | M5: 1. ล็อกอินสำเร็จ และเห็นหน้าจอเดียวกับผู้ใช้ทั่วไป — ระบบไม่มีเมนูหรือหน้ารายการรออนุมัติแยกต่างหาก 2. แถบผู้ใช้แสดง **ชื่อสายงานจริง** ของ Laddawan — ถ้าขึ้นเป็นข้อความ `ไม่ระบุสายงาน` ถือว่า Fail (ข้อนี้เคยเป็นข้อบกพร่องและแก้ไปแล้วหลังรอบ SIT จึงต้องตรวจซ้ำ) 3. ป้ายที่ติดกับฝ่ายที่ค้างอนุมัติในตัวเลือกฝ่ายเขียนว่า `Pending` เป็นภาษาอังกฤษ **ไม่ใช่** คำว่า "รออนุมัติ" — ถ้ายังเห็นเป็นคำไทย ถือว่า Fail 4. ตัวเลขงบของฝ่ายที่ค้างรออนุมัติทุกช่องเป็นแบบอ่านอย่างเดียว คลิกแล้วพิมพ์แก้ไขไม่ได้ 5. เมื่อเลือกฝ่ายที่ค้างอยู่ที่ขั้นของตน จะเห็นปุ่ม `Approve` และ `Reject` ปรากฏบนแถบอนุมัติ (การกดปุ่มจริงอยู่ในเคส UAT-37 และ UAT-38 เคสนี้ตรวจแค่ว่าปุ่มมีอยู่) — หมายเหตุสำคัญ — อย่ากดปุ่ม `Approve` ในเคสนี้ — การอนุมัติทั้งหมดทำตามลำดับในระลอก W6 เท่านั้น เพราะสถานะ `Approved` ย้อนกลับไม่ได้ในระบบ · Laddawan เป็นทั้งผู้กรอกของฝ่าย Data & Analytic และผู้อนุมัติขั้นที่ 1 ของฝ่ายเดียวกัน ดังนั้นตารางจะอ่านอย่างเดียวก็ต่อเมื่อฝ่ายนั้นถูกส่งเข้าอนุมัติแล้ว — ถ้าเปิดฝ่ายที่ยังไม่ได้ส่ง เธอจะยังกรอกได้ตามปกติ และนั่นไม่ใช่ Fail | N5: สวมสิทธิ์ laddawank → หน้าจอเดียวกับผู้ใช้ทั่วไป ไม่มีเมนูรายการรออนุมัติแยก · แถบผู้ใช้: laddawank / laddawank@chememan.com · role badge 'ผู้กรอกงบประมาณ' (เธอเป็นผู้กรอกของฝ่ายเดียวกันด้วย) · สายงาน = 'Digital Technology' (ไม่ใช่ 'ไม่ระบุสายงาน') · ฝ่าย 1 Data & Analytic · 2 COST CENTERS · 10 GL CODES · เปิดตัวเลือกฝ่าย: 'Data & Analytic Pending 2 CC' และ 'Solution Delivery 1 CC' — ป้าย 'Pending' เป็นภาษาอังกฤษ · เลือก Data & Analytic: ช่องงบทุกช่องเป็นข้อความอ่านอย่างเดียว (0 input) ไม่มีปุ่มลบ · แถบอนุมัติ: chip 'Pending · Step 1 (Direct manager)' + 'Submitted — locked for editing until it is rejected' + ปุ่ม Reject และ Approve (ยังไม่กด) | O5: Pass | R5: Laddawan | S5: 46274 | T5: [AI pre-run 09/09/2026] ผ่าน Expected ข้อ 1-5 · ข้อสังเกต: ตัวเลือกฝ่ายของ Laddawan มี Solution Delivery 1 CC ด้วย แม้แถบผู้ใช้จะบอก ฝ่าย 1 — น่าจะมาจากสิทธิ์ 'เห็น' ผ่านการเป็นผู้อนุมัติ ให้คนยืนยันว่าตั้งใจ
A6: W1 | B6: 3 | C6: 4 | D6: UAT-04 | E6: Login / Authentication | F6: - | H6: ออกจากระบบ (Logout) แล้วกดปุ่ม Back ของเบราว์เซอร์ ต้องไม่กลับไปเห็นข้อมูลงบเดิม | I6: Low | J6: ล็อกอินอยู่ในระบบ และเปิดหน้าจอที่มีข้อมูลงบของฝ่ายหนึ่งแสดงอยู่ เพื่อให้รู้ว่ามีข้อมูลอะไรบนจอก่อนออกจากระบบ | K6: 1. ล็อกอินเข้าระบบ เลือกฝ่ายที่มีข้อมูลงบ แล้วจดตัวเลขที่เห็นบนจอไว้ 1 ค่า พร้อมชื่อ Cost Center และเดือนของค่านั้น 2. คลิกลิงก์ `ออกจากระบบ` ที่อยู่มุมขวาของแถบผู้ใช้ด้านบน 3. รอจนระบบพากลับไปหน้าล็อกอิน 4. กดปุ่ม Back ของเบราว์เซอร์ 1 ครั้ง 5. สังเกตหน้าจอที่ได้ แล้วจดลงช่อง Actual Result ว่าเห็นอะไร (หน้าล็อกอิน / หน้าเปล่า / ข้อมูลงบเดิม) | L6: - | M6: 1. ระบบออกจากระบบสำเร็จและกลับไปหน้าล็อกอิน 2. เมื่อกด Back ต้องไม่กลับไปเห็นข้อมูลงบเดิม ระบบต้องบังคับให้ล็อกอินใหม่หรือแสดงหน้าล็อกอิน 3. ไม่มีตัวเลขงบของฝ่ายใดค้างอยู่บนหน้าจอหลังออกจากระบบ — หมายเหตุสำคัญ — ข้อสังเกตที่ยกมาจากรอบ SIT: ถ้าเปิดในหน้าต่างปกติ SSO ของบริษัทอาจพาล็อกอินกลับเข้าระบบให้เองโดยไม่ถามรหัสผ่าน ถ้าเกิดกรณีนี้ให้จดไว้ในช่อง Actual Result และยังถือว่าผ่านได้ ตราบใดที่ไม่เห็นข้อมูลงบเดิมก่อนล็อกอินสำเร็จ · ถ้าต้องการทดสอบให้ชัด ให้ทำซ้ำในหน้าต่าง InPrivate / Incognito | N6: ก่อนออก: หน้า D&A Year 2026 เห็นยอด 415,900.00 / 135,500.00 · คลิก 'ออกจากระบบ' → ระบบพาไป login.microsoftonline.com หน้า 'Sign out — Pick an account: Which account do you want to sign out of? jakkaritw@chememan.com' (หน้าออกจากระบบของ Microsoft) · กด Back 1 ครั้ง → กลับมาที่ URL เดิมของแอป แต่ไม่มีตาราง ไม่มีตัวเลขงบใด ๆ · แสดงกล่อง 'หมดเวลาการเข้าใช้งาน (ระบบให้ล็อกอินได้ครั้งละ 14 ชั่วโมง) กรุณา login ใหม่อีกครั้ง' ปุ่ม 'เข้าสู่ระบบใหม่' และข้อความ 'โหลดข้อมูลผู้ใช้ไม่สำเร็จ — กรุณาลองรีเฟรชหน้าใหม่' | O6: Pass | R6: ไม่ระบุชื่อในเคส (ต่อจากเคสก่อนหน้า น่าจะเป็น Pornthip) | S6: 46274 | T6: [AI pre-run 09/09/2026] ผ่านข้อ 1-3: session ของแอปถูกตัดทันทีตั้งแต่กดออก (ก่อนเลือกบัญชีในหน้า Microsoft) กด Back ไม่เห็นข้อมูลเดิม ถูกบังคับล็อกอินใหม่ · ข้อสังเกต 2 จุด: (ก) กล่องที่เห็นใช้ข้อความ 'หมดเวลาการเข้าใช้งาน … 14 ชั่วโมง' ทั้งที่ผู้ใช้เพิ่งกดออกเอง — ความหมายไม่ตรงเหตุการณ์ (ข) ตัวเลข '14 ชั่วโมง' เขียนตายตัวในข้อความ ขณะที่รอบ UAT ตั้งอายุ session ไว้ 1 ชั่วโมง → คนทำ UAT-05 จะเห็น '14 ชั่วโมง' ทั้งที่หมดเวลาจริงตอน 1 ชั่วโมง ควรอ่านค่าจากการตั้งค่า · jakkaritw ตัดสิน 2026-09-09: ข้อความ 'หมดเวลา … 14 ชั่วโมง' ตอนกดออกจากระบบ ยอมรับได้ ไม่เปิด defect
A7: W1 | B7: 4 | C7: 5 | D7: UAT-05 | E7: Login / Authentication | F7: - | H7: Session อายุ 1 ชั่วโมงหมดอายุ ระบบแสดงกล่อง `หมดเวลาการเข้าใช้งาน` ค่าที่พิมพ์ค้างยังแสดงบนจอแต่ต้องไม่ถูกบันทึก และเมื่อกด `เข้าสู่ระบบใหม่` ต้องกลับมาที่ฝ่ายและปีเดิม | I7: Medium | J7: ทีมพัฒนาปรับอายุ session (cookie) เป็น 1 ชั่วโมงก่อนเริ่มรอบ UAT แล้ว (ค่าจริงคือ 14 ชั่วโมง และจะคืนค่าหลังจบรอบ) · ผู้ทดสอบต้อง **ล็อกอินใหม่หลังปรับค่าแล้วเท่านั้น** เพราะอายุ session นับจากเวลาที่ล็อกอิน ไม่ได้ต่ออายุตามการใช้งาน · ทำเคสนี้กับฝ่ายและปีที่ยัง **แก้ไขได้** คือสถานะบนแถบอนุมัติเป็น `Draft — not submitted` หรือ `Rejected` (ยังไม่ได้ส่งขออนุมัติ หรือถูกตีกลับมาแล้ว) · เผื่อเวลารอไว้ 1 ชั่วโมงเต็ม | K7: 1. ยืนยันกับทีมพัฒนาว่าปรับอายุ session เป็น 1 ชั่วโมงเรียบร้อยแล้ว 2. ล็อกอินใหม่ จดเวลาที่ล็อกอิน และจดฝ่ายกับปีที่กำลังเปิดอยู่ (รวมทั้ง URL บนแถบที่อยู่ของเบราว์เซอร์) 3. เลือกช่องเดือนหนึ่งในตาราง แล้วจด Cost Center / GL / เดือน และ **ตัวเลขเดิมในช่องนั้น** ไว้ 4. พิมพ์ตัวเลขใหม่ลงในช่องนั้น โดย **ยังไม่คลิกออกจากช่อง** 5. ปล่อยหน้าจอทิ้งไว้จนครบ 1 ชั่วโมงนับจากเวลาที่ล็อกอินในข้อ 2 6. คลิกออกจากช่อง เพื่อให้ระบบพยายามบันทึกค่า 7. อ่านกล่องที่เด้งขึ้นมา แล้วจดข้อความในกล่องตรงตามตัวอักษรลงช่อง Actual Result 8. ลองกด Esc และลองคลิกนอกกล่อง เพื่อดูว่าปิดกล่องได้หรือไม่ 9. กดปุ่ม `เข้าสู่ระบบใหม่` แล้วล็อกอินอีกครั้ง 10. เมื่อกลับเข้าระบบแล้ว ตรวจว่าอยู่ที่ฝ่ายและปีเดิมหรือไม่ แล้วเปิดดูค่าในช่องเดิม (ช่องจากข้อ 3) ว่าตอนนี้เป็นค่าใด 11. แจ้งทีมพัฒนาให้คืนค่าอายุ session เดิม (14 ชั่วโมง) หลังจบรอบ UAT | L7: อายุ session ระหว่างรอบ UAT = 1 ชั่วโมง (ค่าจริงบน production = 14 ชั่วโมง) ช่องที่ใช้ทดสอบ: 1 ช่องเดือนของฝ่ายที่ยังแก้ไขได้ (สถานะ `Draft — not submitted` หรือ `Rejected`) จดไว้ 2 ค่า: ค่าเดิมในช่องก่อนพิมพ์ · ค่าใหม่ที่พิมพ์ค้างไว้ | M7: 1. เมื่อครบ 1 ชั่วโมงแล้วสั่งบันทึก ระบบแสดงกล่องหัวข้อ `หมดเวลาการเข้าใช้งาน` และไม่ยอมบันทึกด้วย session เดิม 2. ตัวเลขที่พิมพ์ค้างไว้ยังแสดงอยู่บนหน้าจอ ไม่หายไปทันที 3. กล่องนี้มีทางออกทางเดียวคือปุ่ม `เข้าสู่ระบบใหม่` — ไม่มีปุ่มปิด กด Esc ไม่ปิด และคลิกนอกกล่องก็ไม่ปิด 4. เมื่อกด `เข้าสู่ระบบใหม่` และล็อกอินเสร็จ ระบบพากลับมาที่ฝ่ายและปีงบเดิม (URL เดิม) 5. ค่าที่พิมพ์ค้างตอน session หมดอายุ **ต้องไม่ถูกบันทึก** — ช่องนั้นต้องกลับมาแสดงค่าเดิมก่อนพิมพ์ตามที่จดไว้ในข้อ 3 ของ Test Steps · ถ้าค่ากลายเป็นตัวเลขที่พิมพ์ค้าง ถือว่า Fail 6. ข้อความในกล่องจะเขียนว่า "ระบบให้ล็อกอินได้ครั้งละ 14 ชั่วโมง" ทั้งที่ตั้งค่าไว้ 1 ชั่วโมง — ให้จดไว้เฉย ๆ ถือว่าถูกต้องตามที่ตัดสินแล้ว ไม่ถือเป็นข้อผิดพลาด — หมายเหตุสำคัญ — KNOWN ISSUE ที่ไม่ต้องแจ้งเป็น defect: ข้อความ "14 ชั่วโมง" ในกล่อง `หมดเวลาการเข้าใช้งาน` ไม่ตรงกับอายุ session 1 ชั่วโมงที่ตั้งไว้ระหว่าง UAT — ตัดสินแล้วว่ายอมรับ (jakkaritw 2026-09-06) ห้ามเปิด Defect ข้อนี้ · เคสนี้ต้องรอ 1 ชั่วโมงเต็ม แนะนำให้เริ่มไว้แล้วไปทำเคสอื่นในเครื่อง/เบราว์เซอร์อีกตัวระหว่างรอ · อย่าลืมแจ้งทีมพัฒนาให้คืนค่าอายุ session เป็น 14 ชั่วโมงหลังจบรอบ UAT | N7: ข้อ 1-2: ทีมพัฒนายืนยันอายุ session = 1 ชั่วโมงในรอบ UAT · ล็อกอิน 16:22 (jakkaritw สวมสิทธิ์ Pornthip) เปิดฝ่าย Solution Delivery Year 2026 URL /?dept=Solution%20Delivery&year=2026 · ข้อ 3-4: ช่อง 10IT012000 / GL 6210900060 / ก.พ. ค่าเดิม 0 (ยอดปี 10,000.00) พิมพ์ 200 เมื่อ 17:08 โดยไม่คลิกออก · ข้อ 5: เฝ้าทุก 1 นาที — /me ตอบ 200 จนถึง 17:22:06 และตอบ redirect (session ตาย) ที่ 17:23:06 = อายุจริง ~61 นาทีนับจาก 16:22 · ระหว่างที่ยังไม่บันทึก หน้าจอไม่เด้งกล่องเอง ค่า 200 ยังค้างในช่อง · ข้อ 6-7: คลิกออกจากช่อง 17:23:11 → ระบบไม่บันทึก ขึ้นกล่องทันที หัวข้อ 'หมดเวลาการเข้าใช้งาน' ข้อความ (คำต่อคำ) 'หมดเวลาการเข้าใช้งาน (ระบบให้ล็อกอินได้ครั้งละ 14 ชั่วโมง) กรุณา login ใหม่อีกครั้ง' ปุ่มเดียว 'เข้าสู่ระบบใหม่' · ตัวเลข 200 ที่พิมพ์ยังแสดงอยู่บนจอด้านหลังกล่อง · ข้อ 8: กด Esc → กล่องยังอยู่ · คลิกนอกกล่อง (พื้นหลังมืด) → กล่องยังอยู่ · ไม่มีปุ่มปิด/✕ · ข้อ 9: กด 'เข้าสู่ระบบใหม่' → ไปหน้า login.microsoftonline.com โดย state=redir ชี้กลับมาที่ URL เดิม (/?dept=Solution%20Delivery&year=2026) · เบราว์เซอร์ทดสอบยังถือ cookie ของ Microsoft อยู่ จึงล็อกอินผ่านอัตโนมัติ (SSO) ไม่ต้องกรอกรหัส · ข้อ 10: กลับมาที่ฝ่าย Solution Delivery ปี Year 2026 URL เดิมทันที /me = 200 · ช่อง ก.พ. ของ 6210900060 = 0 (ค่า 200 ไม่ถูกบันทึก) ยอดปี 10,000.00 เท่าเดิม | O7: Pass | R7: ไม่ระบุชื่อในเคส (แนะนำ Pornthip เพราะฝ่ายเธอยังแก้ไขได้) | S7: 46274 | T7: [AI pre-run 09/09/2026] ผ่านทุกข้อ (1-4 ตาม Expected) · ข้อสังเกตที่รับไว้แล้วใน UAT-04: ข้อความในกล่องบอก '14 ชั่วโมง' ตายตัว ทั้งที่รอบนี้หมดอายุจริงที่ ~1 ชั่วโมง · ข้อ 9 ในเครื่องผู้ทดสอบจริงอาจเห็นหน้ากรอกรหัสของ Microsoft แทน SSO อัตโนมัติ — ปลายทางเดียวกัน · ข้อ 11 (คืนอายุ session เป็น 14 ชั่วโมง) อยู่ใน tracker uat-post-run-reset
A8: W2 | B8: 5 | C8: 6 | D8: UAT-06 | E8: Budget Entry (Filler) | F8: Data & Analytic | H8: เปิดตารางกรอกงบของฝ่าย Data & Analytic แล้วตรวจว่าตารางแสดงครบทั้ง 2 ฝั่ง 3 ชั้นข้อมูลต่อแถว 12 เดือน และคอลัมน์ รวมทั้งปี | I8: High | J8: ล็อกอินเป็น Pornthip (pornthipp@chememan.com) ซึ่งเป็นผู้กรอกงบประมาณของฝ่าย Data & Analytic · เปิดระบบจริง (production) · ฝ่าย Data & Analytic มี 2 Cost Center คือ 10IT011300 และ 10IT013000 · ปีงบประมาณ 2027 เป็นปีเดียวที่เปิดรับกรอก และหน้าจอจะแสดงปีนี้เป็น `Year 2026` | K8: 1. เปิด URL ของระบบด้วยเบราว์เซอร์ Chrome แล้วล็อกอินด้วยบัญชีของ Pornthip 2. ที่ toolbar เลือกฝ่าย `Data & Analytic` และเลือกปี `Year 2026` 3. รอให้ตารางโหลดเสร็จ แล้วอ่านหัวตารางทั้งสองฝั่ง จดชื่อที่เห็นลงช่อง Actual Result 4. เลือกแถวใดแถวหนึ่ง แล้วนับว่าในแถวนั้นมีชั้นข้อมูลซ้อนกันกี่ชั้น และจดชื่อของแต่ละชั้น 5. ไล่อ่านหัวคอลัมน์เดือนตั้งแต่ Jan ถึง Dec แล้วนับว่าครบ 12 เดือนหรือไม่ และดูว่ามีคอลัมน์ `รวมทั้งปี` ต่อท้าย 6. เลื่อนลงไปท้ายแต่ละกลุ่ม GL ดูยอดรวมย่อยของกลุ่ม และเลื่อนไปท้ายตารางดูยอดรวมใหญ่ของฝั่งนั้น 7. ตรวจว่า Cost Center ที่ปรากฏในตารางมีเฉพาะ 10IT011300 และ 10IT013000 ตามสิทธิ์จริง | L8: ฝ่าย: Data & Analytic ปีที่หน้าจอแสดง: Year 2026 (= ปีงบประมาณ 2027) Cost Center ที่คาดว่าจะเห็น: 10IT011300 และ 10IT013000 | M8: 1. ตารางแบ่งเป็น 2 ฝั่ง คือ `ฝั่งผลิต / ต้นทุน (5xxx)` และ `ฝั่งบริหาร / ขาย · SG&A (6xxx)` 2. แต่ละแถว (คู่ Cost Center + GL) มีชั้นข้อมูลซ้อนกัน 3 ชั้น คือ `SAP · ใช้จริง` / `Approved · งบ` / `Pending` 3. มีช่องเดือนครบ 12 เดือน Jan ถึง Dec และมีคอลัมน์ `รวมทั้งปี` ต่อท้าย 4. มียอดรวมย่อยของแต่ละกลุ่ม GL และมียอดรวมใหญ่ท้ายตารางของแต่ละฝั่ง 5. ตารางแสดงเฉพาะ Cost Center และ GL ที่อยู่ในสิทธิ์ของ Pornthip ไม่มีฝ่ายอื่นปน — หมายเหตุสำคัญ — เคสนี้เป็นการดูอย่างเดียว ยังไม่ต้องกรอกตัวเลข ให้ทำก่อนเคสอื่นใน wave นี้ เพราะเคสถัดไปอ้างชื่อฝั่งตารางและชื่อชั้นข้อมูลจากเคสนี้ | N8: หัวตาราง: เห็นฝั่งเดียวคือ 'ฝั่งบริหาร / ขาย · SG&A (6xxx)' — ฝั่ง 'ฝั่งผลิต / ต้นทุน (5xxx)' ไม่แสดงเพราะ Data & Analytic ไม่มีแถว GL 5xxx เลย · แต่ละแถวมี 3 ชั้น: SAP · ใช้จริง / APPROVED · งบ / PENDING · รออนุมัติ · หัวเดือน Jan–Dec ครบ 12 และมีคอลัมน์ รวมทั้งปี (Jan–Dec) นำหน้า · ยอดรวมย่อยต่อกลุ่ม: รวม Maintenance - License for software · Pending, รวม Other admin. Expenses · Pending, รวม Travelling Expense · Pending · ยอดรวมใหญ่: รวมทั้งหมด · SAP · ใช้จริง (Jan–Mar) / Approved · งบ / Pending · รออนุมัติ · Cost Center ที่ปรากฏ: 10IT013000 เท่านั้น (GL 6211100110, 6211400010, 6210400010) ไม่มีฝ่ายอื่นปน | O8: Pass | R8: Pornthip | S8: 46274 | T8: [AI pre-run 09/09/2026] ผ่านข้อ 2-5 · ข้อ 1 (ต้องเห็น 2 ฝั่ง): เห็นฝั่งเดียว — ยืนยันจากโค้ด GridTable.tsx:1156 ว่าฝั่งที่ไม่มีแถวถูกซ่อนโดยตั้งใจ จึงไม่ใช่ defect แต่ Expected ข้อ 1 ควรเขียนเพิ่มว่า 'ฝั่งที่ไม่มีแถวจะไม่แสดง' · 10IT011300 ไม่ปรากฏเพราะยังไม่มีแถวใด ๆ (ทั้ง Pending และ SAP) — ตรงเงื่อนไข 'มีเฉพาะ' แต่ควรให้คนยืนยันว่าถูกต้องตามสิทธิ์จริง
A9: W2 | B9: 6 | C9: 7 | D9: UAT-07 | E9: Budget Entry (Filler) | F9: Data & Analytic | H9: ตรวจว่าชั้น `SAP` และชั้น `Approved` แสดงข้อมูลของปีที่วางแผนลบหนึ่ง ป้ายปีบนคำอธิบายตรงกัน ทั้งสองชั้นแก้ไขไม่ได้ และแถวที่มีเฉพาะ Approved ยังต้องปรากฏ | I9: High | J9: ล็อกอินเป็น Pornthip และเปิดตารางของฝ่าย `Data & Analytic` ปี `Year 2026` (ปีงบประมาณ 2027) ไว้แล้ว · ปีที่วางแผนของรอบนี้คือ 2027 ดังนั้นชั้น SAP และชั้น Approved ต้องเป็นข้อมูลของปี 2026 | K9: 1. เปิดตารางของฝ่าย `Data & Analytic` ปี `Year 2026` 2. อ่านคำอธิบายชั้นข้อมูล (legend) เหนือตาราง แล้วจดปีที่กำกับไว้บนชั้น `SAP · ใช้จริง` และบนชั้น `Approved · งบ` ลงช่อง Actual Result 3. คลิกลงไปในช่องเดือนของชั้น `SAP` แล้วลองพิมพ์ตัวเลขทับ 4. คลิกลงไปในช่องเดือนของชั้น `Approved` แล้วลองพิมพ์ตัวเลขทับ 5. ไล่สายตาดูทีละแถวทั้งสองฝั่งของตาราง (กดปุ่มเต็มจอ `⤢` จะเห็นแถวได้มากขึ้น) เพื่อหาแถวที่มีตัวเลขเฉพาะชั้น `Approved` โดยที่ชั้น `SAP` และชั้น `Pending` ว่าง — ช่องกรองด้านบนตารางกรองได้เฉพาะ Cost Center / GL / GL Group / Remark / Status กรองตามชั้นข้อมูลไม่ได้ จึงต้องไล่ดูด้วยตา 6. จดเลข GL และเลข Cost Center ของแถวลักษณะนั้นลงช่อง Actual Result (ถ้าไม่พบให้บันทึกว่าไม่พบ) | L9: ปีที่วางแผน = 2027 → ชั้น `SAP · ใช้จริง` และ `Approved · งบ` ต้องเป็นข้อมูลของปี 2026 ชั้น `Pending` เท่านั้นที่เป็นปี 2027 | M9: 1. ป้ายปีที่กำกับชั้น `SAP · ใช้จริง` และชั้น `Approved · งบ` เป็นปีที่วางแผนลบหนึ่ง คือปี 2026 และตรงกันทั้งบนคำอธิบายและในตาราง 2. ชั้น `SAP` แก้ไขไม่ได้ พิมพ์ทับไม่ได้ 3. ชั้น `Approved` แก้ไขไม่ได้ พิมพ์ทับไม่ได้ 4. แถวที่มีตัวเลขเฉพาะชั้น `Approved` โดยไม่มีข้อมูล SAP และไม่มี Pending ต้องยังปรากฏในตาราง ไม่ถูกซ่อนหายไป 5. ถ้าค้นแล้วไม่พบแถวลักษณะข้อ 4 ในฝ่ายนี้ ให้บันทึกลงช่อง Actual Result ว่าไม่พบ อย่าเดาผลเป็น Pass — หมายเหตุสำคัญ — ชั้น SAP และชั้น Approved เป็นข้อมูลของปีก่อนโดยการออกแบบ ผู้กรอกใช้เป็นฐานในการวางแผนปีหน้า ไม่ใช่ข้อผิดพลาด · ถ้าปีที่กำกับไม่ใช่ 2026 นั่นคือของจริงที่ต้องแจ้งเป็น defect | N9: legend: 'SAP · ใช้จริง (2026)' และ 'Approved · งบอนุมัติ (2026)' = ปีวางแผน 2027 ลบหนึ่ง ตรงกัน · ชั้น SAP เป็นเซลล์ข้อความ (data-testid sap-value-*) ไม่มี input พิมพ์ทับไม่ได้ · ชั้น Approved เป็นเซลล์ข้อความ (board-value-*) ไม่มี input พิมพ์ทับไม่ได้ · ข้อ 5-6: ไล่ทุกแถวของ Data & Analytic แล้ว ไม่พบแถวที่มีตัวเลขเฉพาะชั้น Approved — ชั้น Approved ว่างทุกแถว (รวมทั้งหมด · Approved · งบ = —) | O9: Pass | R9: Pornthip | S9: 46274 | T9: [AI pre-run 09/09/2026] ข้อ 1-3 ผ่าน · ข้อ 4 ตรวจไม่ได้ในฝ่ายนี้เพราะไม่มีแถว Approved-only เลย บันทึกว่า 'ไม่พบ' ตาม Expected ข้อ 5 ไม่ถือเป็น Fail · ถ้าต้องการพิสูจน์ข้อ 4 จริง ต้องใช้ฝ่ายที่มีข้อมูล board_budget ปี 2026
A10: W2 | B10: 7 | C10: 8 | D10: UAT-08 | E10: Budget Entry (Filler) | F10: Data & Analytic | H10: ตรวจว่าเดือนที่ข้อมูล SAP ยังไม่ครบแสดงเป็นขีด `–` พร้อมคำอธิบายเมื่อเอาเมาส์วาง และยอดรวมทั้งปีของชั้น SAP มีข้อความกำกับว่านับเฉพาะเดือนที่ข้อมูลครบ | I10: Low | J10: ล็อกอินเป็น Pornthip และเปิดตารางของฝ่าย `Data & Analytic` ปี `Year 2026` ไว้แล้ว · ระบบจะซ่อนตัวเลข SAP ของเดือนที่ข้อมูลยังเข้ามาไม่ครบ ซึ่งเป็นกติกาที่ตั้งใจให้เป็น | K10: 1. เปิดตารางของฝ่าย `Data & Analytic` ปี `Year 2026` 2. ไล่ดูชั้น `SAP · ใช้จริง` ทั้ง 12 เดือน หาช่องที่แสดงเป็นขีด `–` แทนตัวเลข 3. เอาเมาส์ไปวางค้างบนขีด `–` แล้วอ่านข้อความที่ขึ้นมา คัดลอกลงช่อง Actual Result 4. เอาเมาส์ไปวางค้างบนยอด `รวมทั้งปี` ของชั้น `SAP` — ข้อความกำกับเป็นคำอธิบายที่ขึ้นเมื่อวางเมาส์ ไม่ได้พิมพ์ไว้บนหน้าจอ จึงต้องวางเมาส์ค้างจึงจะเห็น แล้วคัดลอกข้อความที่ขึ้นมาลงช่อง Actual Result 5. จดว่าเดือนไหนบ้างที่แสดงเป็นขีด | L10: ชั้นที่ตรวจ: `SAP · ใช้จริง` ของฝ่าย Data & Analytic สิ่งที่มองหา: ช่องเดือนที่แสดงเป็นขีด `–` แทนตัวเลข | M10: 1. ช่องเดือนที่ข้อมูล SAP ยังไม่ครบแสดงเป็นขีด `–` ไม่ใช่เลข 0 (เพื่อไม่ให้ผู้ใช้เข้าใจผิดว่าเดือนนั้นไม่มีค่าใช้จ่าย) 2. เอาเมาส์วางบนขีดแล้วขึ้นข้อความ `ข้อมูล SAP เดือนนี้ยังไม่ครบ จึงยังไม่แสดง` 3. เอาเมาส์วางค้างบนยอด `รวมทั้งปี` ของชั้น SAP แล้วขึ้นข้อความกำกับว่า `รวมเฉพาะเดือนที่ข้อมูลครบ:` ตามด้วยช่วงเดือนที่นับรวมไว้ 4. ผู้ทดสอบอ่านแล้วเข้าใจว่าทำไมเดือนนั้นไม่มีตัวเลข — ถ้าอ่านแล้วยังงง ให้เขียนคำที่อยากให้แก้ลงช่อง Remarks 5. ถ้าทุกเดือนของฝ่ายนี้มีข้อมูลครบจนไม่พบขีด `–` เลย ให้บันทึกผลเป็น N/A พร้อมระบุเหตุผล ไม่ต้องนับเป็น Fail — หมายเหตุสำคัญ — เคสนี้ตรวจว่าผู้ใช้เข้าใจการซ่อนข้อมูลหรือไม่ ไม่ใช่การกระทบยอด SAP กับ SAP ซึ่งอยู่นอกขอบเขตของ UAT รอบนี้ | N10: ชั้น SAP: เดือน Apr–Dec (m04–m12) แสดงเป็นขีด '–' (ข้อมูลยังไม่ครบ) · Jan–Feb แสดง '—' (ครบแต่เป็นศูนย์) · Mar มีตัวเลข 844.91 / 500.00 · tooltip บนขีด = 'ข้อมูล SAP เดือนนี้ยังไม่ครบ จึงยังไม่แสดง' · tooltip บนยอดรวมทั้งปีชั้น SAP = 'รวมเฉพาะเดือนที่ข้อมูลครบ: Jan–Mar' และหัวยอดรวมใหญ่เขียน 'รวมทั้งหมด · SAP · ใช้จริง (Jan–Mar)' | O10: Pass | R10: Pornthip | S10: 46274 | T10: [AI pre-run 09/09/2026] ข้อ 1-3 ตรงตาม Expected ทุกตัวอักษร · ข้อ 4 เป็นความเห็นของคนว่าอ่านแล้วเข้าใจไหม — AI ไม่ตัดสินแทน ให้ผู้ทดสอบยืนยันแล้วเปลี่ยน Status เป็น Pass เอง · jakkaritw ตัดสิน 2026-09-09: อ่านเข้าใจ / ยอมรับได้ → Pass
A11: W2 | B11: 8 | C11: 9 | D11: UAT-09 | E11: Budget Entry (Filler) | F11: Data & Analytic | H11: กรอกจำนวนเงินในช่องเดือนแล้วคลิกออกจากช่อง ระบบต้องบันทึกให้อัตโนมัติโดยไม่มีปุ่ม Save และค่ายังอยู่หลังโหลดหน้าใหม่ | I11: High | J11: ล็อกอินเป็น Pornthip · อยู่ในตารางกรอกงบของฝ่าย `Data & Analytic` ปี `Year 2026` ซึ่งยังแก้ไขได้ (ยังไม่ได้ส่งขออนุมัติในรอบนี้ หรือเคยถูกตีกลับมาแล้วจึงยังกรอกได้) · ทีมทดสอบตกลงกันแล้วว่าจะใช้แถวไหนและเดือนไหนเป็นช่องทดสอบ | K11: 1. เลือกช่องเดือนหนึ่งในชั้น `Pending` ของ Cost Center 10IT011300 แล้วจดค่าเดิมในช่องนั้นไว้ก่อน 2. พิมพ์จำนวนเงินลงในช่อง 3. คลิกนอกช่อง — ระบบไม่มีปุ่ม Save การบันทึกเกิดขึ้นเองเมื่อคลิกออกจากช่อง 4. รอจนข้อความ `กำลังบันทึก…` แสดงขึ้นแล้วหายไปเอง 5. กด refresh โหลดหน้าใหม่ทั้งหน้า 6. กลับมาดูช่องเดิมว่าค่ายังอยู่หรือไม่ 7. จดป้ายสถานะของฝ่ายที่แสดงอยู่บนแถบอนุมัติลงช่อง Actual Result | L11: จำนวนเงินที่ใช้ทดสอบ: 100,000 หรือ 250,000 (ให้เลือกจำนวนที่ลงท้ายด้วย 00 เพราะระบบปัดค่าเป็นหลักร้อย — กติกาการปัดจะถูกทดสอบแยกในเคส UAT-12) | M11: 1. พิมพ์แล้วคลิกออกจากช่อง ระบบบันทึกให้เอง โดยไม่มีปุ่ม Save ให้กด 2. ข้อความ `กำลังบันทึก…` ขึ้นระหว่างบันทึกแล้วหายไปเองเมื่อบันทึกเสร็จ 3. หลังโหลดหน้าใหม่ ค่าที่กรอกยังอยู่ครบ ไม่หายและไม่กลับไปเป็นค่าเดิม 4. ป้ายสถานะของฝ่ายบนแถบอนุมัติแสดงเป็นภาษาอังกฤษ ไม่ใช่ข้อความไทยแบบเดิม — ถ้าฝ่ายนี้ยังไม่เคยส่งขออนุมัติในรอบปีนี้ ป้ายต้องเป็น `Draft — not submitted` · ถ้าฝ่ายเคยถูกตีกลับมาก่อน ป้ายจะเป็นข้อความภาษาอังกฤษอีกแบบหนึ่ง ให้จดข้อความที่เห็นจริงลงช่อง Actual Result ทั้งสองกรณีถือว่าผ่านตราบใดที่ยังกรอกและแก้ไขได้ — หมายเหตุสำคัญ — UAT รอบนี้รันบนระบบจริง ค่าที่กรอกถูกเขียนลงฐานข้อมูลจริงของปีงบประมาณ 2027 · เมื่อทดสอบเสร็จให้แก้ค่ากลับเป็นตัวเลขที่ฝ่ายต้องการใช้จริง | N11: ช่องทดสอบ: Pending ของ 10IT013000 / 6211100110 เดือน Jan ค่าเดิม 0 · พิมพ์ 100000 แล้วออกจากช่อง (Tab) ไม่มีปุ่ม Save · รวมทั้งปีของแถวขึ้นเป็น 100,000.00 ทันที · reload ทั้งหน้าแล้วช่อง Jan ยังเป็น 100000 รวมทั้งปี 100,000.00 · ป้ายสถานะบนแถบอนุมัติ = 'Draft — not submitted' (อังกฤษ) และยังกรอกได้ | O11: Pass | R11: Pornthip | S11: 46274 | T11: [AI pre-run 09/09/2026] ผ่านข้อ 1, 3, 4 · ข้อ 2 (ข้อความ 'กำลังบันทึก…' ขึ้นแล้วหายเอง) automation อ่านหน้าจอไม่ทันช่วงสั้น ๆ นั้น จึงยังไม่ได้ยืนยันด้วยตา — ให้ผู้ทดสอบสังเกตในรอบจริง · เบี่ยงเบนจาก step 1: เคสระบุให้ใช้ Cost Center 10IT011300 แต่ CC นั้นไม่มีแถวใดในตารางเลย (ยังไม่ได้เพิ่มรายการ) จึงใช้ 10IT013000 แทน — ควรแก้เคสให้เพิ่มแถวก่อน หรือระบุ 10IT013000
A12: W2 | B12: 9 | C12: 10 | D12: UAT-10 | E12: Budget Entry (Filler) | F12: Data & Analytic | H12: ตรวจว่ายอด `รวมทั้งปี` ของแถว ยอดรวมย่อยของกลุ่ม GL และยอดรวมใหญ่ของฝั่งตาราง คำนวณถูกต้องและขยับทันทีที่กรอก | I12: High | J12: ล็อกอินเป็น Pornthip · อยู่ในตารางกรอกงบของฝ่าย `Data & Analytic` ปี `Year 2026` ที่ยังแก้ไขได้ · เตรียมเครื่องคิดเลขไว้บวกเลขเทียบกับที่ระบบแสดง | K12: 1. เลือกแถวหนึ่งในชั้น `Pending` แล้วจดค่า 3 อย่างไว้ก่อนเริ่ม คือ ยอด `รวมทั้งปี` ของแถวนั้น ยอดรวมย่อยของกลุ่ม GL ที่แถวนี้อยู่ และยอดรวมใหญ่ท้ายฝั่งตาราง 2. กรอก 10,000 ลงช่องเดือนแรกที่ว่าง แล้วคลิกออกจากช่อง 3. กรอก 20,000 ลงช่องเดือนถัดไป แล้วคลิกออกจากช่อง 4. กรอก 5,500 ลงช่องเดือนถัดไปอีกช่อง แล้วคลิกออกจากช่อง 5. อ่านยอด `รวมทั้งปี` ของแถวนั้น แล้วเทียบกับผลบวกที่คำนวณด้วยเครื่องคิดเลข 6. อ่านยอดรวมย่อยของกลุ่ม GL และยอดรวมใหญ่ท้ายฝั่งตารางอีกครั้ง แล้วเทียบกับค่าที่จดไว้ในข้อ 1 7. จดตัวเลขทั้งก่อนและหลังกรอกลงช่อง Actual Result | L12: 10,000 + 20,000 + 5,500 = 35,500 (ทุกจำนวนลงท้ายด้วย 00 อยู่แล้ว จึงไม่ถูกกติกาการปัดหลักร้อยเปลี่ยนค่า) | M12: 1. ยอด `รวมทั้งปี` ของแถวนั้นเพิ่มขึ้น 35,500 จากค่าที่จดไว้ก่อนเริ่ม 2. ยอดรวมย่อยของกลุ่ม GL ที่แถวนี้อยู่ เพิ่มขึ้น 35,500 เท่ากัน 3. ยอดรวมใหญ่ท้ายฝั่งตาราง เพิ่มขึ้น 35,500 เท่ากัน 4. ตัวเลขทั้ง 3 จุดขยับให้เห็นทันทีโดยไม่ต้องโหลดหน้าใหม่ 5. ตัวเลขแสดงคั่นหลักพันอ่านง่าย ไม่มีจุดใดที่ผลบวกเพี้ยนจากเครื่องคิดเลข — หมายเหตุสำคัญ — ตัวเลขที่กรอกในเคสนี้ถูกบันทึกลงระบบจริง เมื่อทดสอบเสร็จให้แก้กลับเป็นตัวเลขที่ฝ่ายต้องการใช้จริง | N12: แถว 10IT013000 / 6211100110 · ก่อน: รวมทั้งปี 100,000.00 / รวมกลุ่ม Maintenance - License for software · Pending 100,000.00 / รวมทั้งหมด · Pending 100,000.00 · กรอก Feb 10,000, Mar 20,000, Apr 5,500 · หลัง: รวมทั้งปี 135,500.00 / รวมกลุ่ม 135,500.00 / รวมทั้งหมด 135,500.00 — ทั้ง 3 จุดเพิ่มขึ้น 35,500.00 พอดี (10,000 + 20,000 + 5,500) ขยับทันทีโดยไม่ต้อง reload · ตัวเลขคั่นหลักพันและมีทศนิยม 2 ตำแหน่ง | O12: Pass | R12: Pornthip | S12: 46274 | T12: [AI pre-run 09/09/2026] ผ่านข้อ 1-5 ทุกข้อ ผลบวกตรงเครื่องคิดเลข
A13: W2 | B13: 10 | C13: 11 | D13: UAT-11 | E13: Budget Entry (Filler) | F13: Data & Analytic | H13: ผู้กรอกต้องเห็นหมายเหตุอธิบายกติกาการกรอกเงินใต้ toolbar ก่อนเริ่มกรอกตัวเลข | I13: Medium | J13: ล็อกอินเป็น Pornthip และเพิ่งเปิดหน้ากรอกงบของฝ่าย `Data & Analytic` ปี `Year 2026` โดยยังไม่กรอกอะไรเลย | K13: 1. เปิดหน้ากรอกงบของฝ่าย `Data & Analytic` ปี `Year 2026` 2. ยังไม่ต้องกรอกตัวเลขใด ๆ 3. อ่านแถบใต้ toolbar บริเวณคำอธิบายชั้นข้อมูล (legend) 4. คัดลอกข้อความหมายเหตุที่เห็นทั้งบรรทัดลงช่อง Actual Result 5. ตอบคำถามในใจว่า อ่านแล้วรู้หรือไม่ว่าต้องกรอกอย่างน้อยเท่าไร และระบบจะปัดเศษอย่างไร | L13: ข้อความที่คาดว่าจะเห็น ขึ้นต้นว่า `หมายเหตุ: กรอกได้ตั้งแต่ 100 ขึ้นไป …` | M13: 1. ใต้ toolbar มีบรรทัดหมายเหตุอธิบายกติกาการกรอกเงิน ขึ้นต้นว่า `หมายเหตุ: กรอกได้ตั้งแต่ 100 ขึ้นไป …` 2. หมายเหตุนี้เห็นได้ตั้งแต่ก่อนเริ่มกรอก ไม่ใช่เห็นหลังจากกรอกผิดไปแล้ว 3. ผู้ทดสอบอ่านแล้วเข้าใจว่าต้องกรอกอย่างน้อย 100 และระบบจะปัดค่าเป็นหลักร้อย — หมายเหตุสำคัญ — ข้อนี้วัดว่าผู้ใช้เข้าใจกติกาก่อนกรอกหรือไม่ ไม่ใช่วัดแค่ว่ามีข้อความอยู่จริง · ถ้าอ่านแล้วยังไม่เข้าใจ ให้เขียนคำที่อยากให้แก้ลงช่อง Remarks แม้ผลจะเป็น Pass | N13: เปิดหน้า Data & Analytic Year 2026 โดยยังไม่กรอกอะไร ใต้ toolbar ข้าง legend มีบรรทัด: 'หมายเหตุ: กรอกได้ตั้งแต่ 100 ขึ้นไป โดยระบบจะปรับตัวเลข 2 หลักสุดท้ายเป็น 00 โดยอัตโนมัติ' เห็นก่อนเริ่มกรอก | O13: Pass | R13: Pornthip | S13: 46274 | T13: [AI pre-run 09/09/2026] ข้อ 1-2 ตรง Expected · ข้อ 3 (อ่านแล้วเข้าใจไหม) เป็นความเห็นของคน — ให้ผู้ทดสอบยืนยันแล้วเปลี่ยนเป็น Pass เอง · jakkaritw ตัดสิน 2026-09-09: อ่านเข้าใจ / ยอมรับได้ → Pass
A14: W2 | B14: 11 | C14: 12 | D14: UAT-12 | E14: Budget Entry (Filler) | F14: Data & Analytic | H14: กติกาช่องกรอกเงินทั้ง 6 กรณีในเคสเดียว — ปัดเป็นหลักร้อย ค่าต่ำกว่า 100 เพดาน 100 ล้าน ทศนิยม ตัวอักษร และค่าติดลบ | I14: High | J14: ล็อกอินเป็น Pornthip · อยู่ในตารางกรอกงบของฝ่าย `Data & Analytic` ปี `Year 2026` ที่ยังแก้ไขได้ · เลือกแถวทดสอบ 1 แถว แล้วในแถวนั้นเตรียมช่องเดือนไว้ 2 ชุด คือ (ก) `ช่องทดสอบหลัก` 1 ช่อง ใช้กับบรรทัดที่ 1, 2, 3, 5 และ 6 และ (ข) `ช่องทดสอบทศนิยม` อีก 3 ช่องที่ตอนนี้ยังเป็น 0 หรือว่างอยู่ ใช้กับบรรทัดที่ 4 โดยเฉพาะ (ต้องเป็นคนละช่องกับช่องทดสอบหลัก) · จดค่าเดิมของทั้ง 4 ช่องไว้ก่อนเริ่ม เพื่อใช้แก้กลับตอนจบเคส · ยอด `รวมทั้งปี` ของแถวนั้นจดไว้ก่อนเริ่มได้เป็นข้อมูลอ้างอิงเท่านั้น **ห้ามใช้เป็นตัวตั้งของบรรทัดที่ 4** เพราะบรรทัดที่ 1 ถึง 3 จะเปลี่ยนค่าในแถวเดียวกันนี้ไปก่อน (บรรทัดที่ 3 ทิ้ง `ช่องทดสอบหลัก` ไว้ที่ `100,000,000`) — บรรทัดที่ 4 ต้องอ่านยอด `รวมทั้งปี` ใหม่สด ๆ ตอนนั้น ตาม Test Steps ข้อ 7 · เตรียมเครื่องคิดเลขไว้บวกยอดของบรรทัดที่ 4 และเตรียมนาฬิกาจับเวลาเพื่อดูว่ากล่องข้อความหายไปเองภายในกี่วินาที · เคสนี้เป็นหนึ่งแถวบนชีต แต่มี 6 บรรทัดที่ต้องยืนยันผลแยกกัน ทำทีละบรรทัด ห้ามรวบ | K14: 1. เริ่มที่บรรทัดที่ 1 ของตาราง Test Data: ที่ `ช่องทดสอบหลัก` ให้ลบค่าเดิมในช่องออกให้หมดก่อน แล้วพิมพ์ค่าของบรรทัดนั้นลงไป 2. คลิกออกจากช่อง แล้วดูทันทีว่าช่องกลายเป็นค่าอะไร 3. มองมุมจอว่ามีกล่องข้อความแจ้งเตือนเด้งขึ้นหรือไม่ — ถ้ามี ให้คัดลอกข้อความนั้นทั้งบรรทัด และจับเวลาว่าหายไปเองภายในประมาณ 6 วินาทีหรือไม่ ถ้าไม่มี ให้เขียนว่า "ไม่มีข้อความ" 4. ดูยอด `รวมทั้งปี` ของแถวนั้นว่าขยับตามค่าที่ระบบปรับให้จริง (ไม่ใช่ตามค่าที่พิมพ์) 5. บันทึกผลของบรรทัดนี้ลงช่อง Actual Result โดยระบุ 3 อย่างเสมอ คือ ค่าที่ได้ในช่อง / ข้อความที่เห็น (หรือเขียนว่า "ไม่มีข้อความ") / ยอดรวมหลังกรอก 6. ทำซ้ำข้อ 1 ถึง 5 กับบรรทัดที่ 2 และบรรทัดที่ 3 ทีละบรรทัด ในช่องทดสอบหลักช่องเดิม 7. บรรทัดที่ 4 ทำไม่เหมือนบรรทัดอื่น เพราะเป็นการตรวจว่าการปัดเศษ **สะสมหลายช่อง** แล้วยอดรวมเพี้ยนหรือไม่ · เริ่มด้วยการอ่านยอด `รวมทั้งปี` ของแถวนั้น **ใหม่อีกครั้งเดี๋ยวนั้น ก่อนพิมพ์ค่าใด ๆ ของบรรทัดนี้** แล้วจดไว้เป็น `ยอดตั้งต้นของบรรทัดที่ 4` — ต้องเป็นตัวเลขที่อ่านสดตอนนี้เท่านั้น ห้ามใช้ยอดรวมที่จดไว้ก่อนเริ่มเคส เพราะบรรทัดที่ 1 ถึง 3 เพิ่งเปลี่ยนค่าในแถวเดียวกันนี้ไปแล้ว · จากนั้นพิมพ์ `33333.33` ลงใน `ช่องทดสอบทศนิยม` ช่องที่ 1 แล้วคลิกออกจากช่อง จดค่าที่ได้ · ทำแบบเดียวกันกับช่องที่ 2 และช่องที่ 3 จนครบทั้งสามช่อง · แล้วอ่านยอด `รวมทั้งปี` ของแถวอีกครั้ง จดไว้เป็น `ยอดหลังของบรรทัดที่ 4` · เอาเครื่องคิดเลขลบกัน: `ยอดหลังของบรรทัดที่ 4` ลบด้วย `ยอดตั้งต้นของบรรทัดที่ 4` ต้องได้ `9,999,900` พอดี · จดค่าของแต่ละช่อง ยอดตั้งต้นของบรรทัดที่ 4 และยอดหลังของบรรทัดที่ 4 ลงช่อง Actual Result 8. บรรทัดที่ 5 ทำที่ `ช่องทดสอบหลัก` และ **ต้องพิมพ์ต่อท้ายค่าเดิมที่อยู่ในช่อง ห้ามลบค่าเดิมออกก่อน**: คลิกในช่อง กดปุ่มลูกศรขวาจนเคอร์เซอร์ไปอยู่ท้ายตัวเลขเดิม แล้วพิมพ์ `abc` ต่อท้าย จากนั้นคลิกออกจากช่อง · ทำซ้ำอีกครั้งด้วย `@#$` ต่อท้ายค่าเดิมเช่นกัน · แล้วทำตามข้อ 2 ถึง 5 ต่อ 9. บรรทัดที่ 6 ทำที่ `ช่องทดสอบหลัก` โดยคราวนี้ให้ลบค่าเดิมออกให้หมดก่อน แล้วพิมพ์ `-5000` ลงไป (บรรทัดนี้ต้องลบค่าเดิมก่อน ไม่อย่างนั้นเลขจะไปต่อท้ายค่าเดิมกลายเป็นตัวเลขคนละตัว และจะอ่านผลไม่ได้) · แล้วทำตามข้อ 2 ถึง 5 ต่อ 10. เมื่อครบทั้ง 6 บรรทัด ให้แก้ค่าในช่องทดสอบทั้ง 4 ช่อง (ช่องทดสอบหลัก 1 ช่อง และช่องทดสอบทศนิยม 3 ช่อง) กลับเป็นตัวเลขที่ฝ่ายต้องการใช้จริง | L14: บรรทัดที่ 1 — ช่องทดสอบหลัก พิมพ์ `146` → คาดว่าช่องกลายเป็น `100` บรรทัดที่ 2 — ช่องทดสอบหลัก พิมพ์ `30` → คาดว่าช่องกลายเป็น `0` บรรทัดที่ 3 — ช่องทดสอบหลัก พิมพ์ `999999999999` (สิบสองหลัก) → คาดว่าช่องกลายเป็น `100,000,000` · ต้องพิมพ์ครบสิบสองหลักตามนี้เป๊ะ ๆ ห้ามย่อให้สั้นลง เพราะนี่คือค่าเดิมที่ SIT กรอกแล้วหน้าจอแสดงเป็นสัญลักษณ์ infinity บรรทัดที่ 4 — ช่องทดสอบทศนิยม 3 ช่อง พิมพ์ `33333.33` ลงไปทั้ง 3 ช่อง (ช่องละครั้ง) → คาดว่าแต่ละช่องกลายเป็น `3,333,300` และยอด `รวมทั้งปี` ของแถวเพิ่มขึ้น 9,999,900 พอดี (3,333,300 × 3) บรรทัดที่ 5 — ช่องทดสอบหลัก พิมพ์ `abc` แล้วลอง `@#$` โดย **พิมพ์ต่อท้ายค่าเดิม ห้ามลบค่าเดิมออกก่อน** → คาดว่าช่องไม่รับตัวอักษร ค่าเดิมคงอยู่เท่าเดิม บรรทัดที่ 6 — ช่องทดสอบหลัก ลบค่าเดิมออกให้หมดก่อน แล้วพิมพ์ `-5000` → คาดว่าเครื่องหมายลบถูกตัดทิ้ง ช่องกลายเป็น `5,000` | M14: ⚠ เคสรวม (merged) — 1 แถวแต่มีหลายข้อที่ต้องตรวจ อ่านให้ครบทุกข้อก่อนตัดสิน Pass 1. บรรทัดที่ 1: `146` → ช่องกลายเป็น `100` และมีกล่องข้อความเด้งมุมจอว่า `กรอก 146 · ระบบปรับเป็น 100 (ปัดเศษเป็นหลักร้อย)` ซึ่งหายไปเองภายในประมาณ 6 วินาที 2. บรรทัดที่ 2: `30` → ช่องกลายเป็น `0` และมีข้อความว่า `กรอก 30 ซึ่งต่ำกว่า 100 · ระบบบันทึกเป็น 0 (กรอกได้ตั้งแต่ 100 ขึ้นไป)` 3. บรรทัดที่ 3: `999999999999` → ช่องกลายเป็น `100,000,000` และมีข้อความแจ้งว่าเกินเพดาน 100 ล้านต่อช่อง (ข้อความที่คาดว่าจะเห็นคือ `กรอก 999,999,999,999 ซึ่งเกินเพดาน 100 ล้านต่อช่อง · ระบบบันทึกเป็น 100,000,000`) · สิ่งที่กำลังพิสูจน์ซ้ำในบรรทัดนี้คือค่าสิบสองหลักชุดนี้โดยเฉพาะ เพราะตอน SIT ค่านี้ทำให้หน้าจอแสดงเป็นสัญลักษณ์ infinity — ตอนนี้ต้องไม่มีสัญลักษณ์ infinity โผล่ทั้งในช่องและในยอดรวมอีก 4. บรรทัดที่ 4 (ดูทีละช่อง): `33333.33` → ระบบไม่รับ **จุด** ทศนิยม จึงตัดเฉพาะจุดทิ้ง ไม่ได้ตัดตัวเลขหลังจุดทิ้ง ค่าที่พิมพ์จึงกลายเป็น `3333333` ก่อน แล้วจึงปัดเป็นหลักร้อยได้ `3,333,300` — ทั้ง 3 ช่องต้องได้ `3,333,300` เท่ากันทุกช่อง 5. บรรทัดที่ 4 (ยอดรวม — ข้อสำคัญที่สุดของบรรทัดนี้): หลังกรอกครบทั้ง 3 ช่อง ยอด `รวมทั้งปี` ของแถวต้อง **เพิ่มขึ้นจาก `ยอดตั้งต้นของบรรทัดที่ 4`** (ตัวเลขที่อ่านสดก่อนพิมพ์ค่าแรกของบรรทัดนี้ ตาม Test Steps ข้อ 7) เท่ากับ 9,999,900 พอดี (3,333,300 + 3,333,300 + 3,333,300) ไม่ขาดไม่เกินแม้แต่บาทเดียว · ตัวตั้งที่ใช้เทียบคือยอดที่อ่านสดก่อนเริ่มบรรทัดนี้เท่านั้น **ห้ามเอายอดรวมที่จดไว้ก่อนเริ่มเคสมาเทียบ** เพราะบรรทัดที่ 1 ถึง 3 เปลี่ยนค่าในแถวเดียวกันนี้ไปแล้ว (บรรทัดที่ 3 ทิ้ง `ช่องทดสอบหลัก` ไว้ที่ 100,000,000) ถ้าเอายอดก่อนเริ่มเคสมาเทียบ ตัวเลขจะห่างกันประมาณร้อยล้านบาทและกลายเป็น Fail ทั้งที่ระบบทำถูก · ย้ำว่ายอดที่ถูกต้องคือผลบวกของ **ค่าที่ระบบปรับแล้ว** ไม่ใช่ผลบวกของค่าที่พิมพ์ (33,333.33 × 3) · ถ้าผลต่างเพี้ยนไปจาก 9,999,900 แม้เพียงเล็กน้อย ให้บันทึกเป็น Fail พร้อมจดตัวเลขที่เห็นจริง 6. บรรทัดที่ 5: พิมพ์ `abc` และ `@#$` ต่อท้ายค่าเดิม → ช่องไม่รับตัวอักษรและสัญลักษณ์เลยแม้แต่ตัวเดียว ค่าเดิมในช่องไม่เปลี่ยน และไม่มีกล่องข้อความเด้งขึ้น · หมายเหตุสำคัญ ถ้าเผลอลบค่าเดิมออกจนช่องว่างก่อนพิมพ์ ระบบจะบันทึกช่องนั้นเป็น `0` โดยไม่มีข้อความแจ้งเตือนใด ๆ — ช่องว่างมีค่าเท่ากับ 0 เป็นการออกแบบไว้แบบนั้น ไม่ใช่ข้อผิดพลาด ให้พิมพ์ค่ากลับเข้าไปแล้วทดสอบบรรทัดนี้ใหม่โดยพิมพ์ต่อท้าย 7. บรรทัดที่ 6: `-5000` → เครื่องหมายลบถูกตัดทิ้ง ช่องจึงบันทึกเป็น `5,000` ซึ่งไม่ใช่ค่าติดลบ และไม่ใช่ค่าเดิมของช่องด้วย · ไม่มีกล่องข้อความเด้งขึ้น เพราะ 5,000 ลงท้ายด้วย 00 อยู่แล้วจึงไม่ถูกปัดค่า 8. ทุกบรรทัด: ยอด `รวมทั้งปี` ของแถวนั้นขยับตามค่าที่ระบบปรับให้จริง ไม่ใช่ตามค่าที่พิมพ์ลงไป 9. ทุกบรรทัด: ต้องบันทึกให้ชัดว่ามีข้อความแจ้งเตือนหรือไม่มี — ผู้ทดสอบ SIT เคยติงว่าบางกรณีระบบไม่แจ้งอะไรเลย ถ้าบรรทัดใดเงียบให้เขียนความเห็นลงช่อง Remarks ว่ายอมรับได้หรือไม่ — หมายเหตุสำคัญ — เคสนี้รวม 4 เคสเดิมจาก SIT (TC-011, TC-012, TC-013, TC-035) ไว้ในแถวเดียว เป็นหนึ่งแถวบนชีตแต่มี 6 บรรทัดที่ต้องยืนยันผลแยกกัน ให้อ่าน Expected Result ให้ครบทั้ง 9 ข้อก่อนกด Pass · บรรทัดที่ 3 คือการทดสอบซ้ำที่ SIT ขอไว้แล้วยังไม่เคยได้ทำ — TC-013 กรอก `999999999999` แล้วหน้าจอแสดงผลเป็นสัญลักษณ์ infinity จึงต้องใช้ค่าสิบสองหลักชุดเดิมเป๊ะ ๆ ไม่ใช่ค่าที่สั้นกว่านั้น ไม่อย่างนั้นถือว่ายังไม่ได้ทดสอบซ้ำตามที่ SIT ขอ · บรรทัดที่ 4 มาจาก TC-035 ซึ่งของเดิมกรอก 33,333.33 หลายรายการเพื่อดูว่าปัดเศษสะสมกันแล้วยอดรวมคลาดเคลื่อนหรือไม่ จึงต้องกรอกให้ครบ 3 ช่องและตรวจยอด `รวมทั้งปี` ด้วย การกรอกช่องเดียวไม่ครอบคลุมสิ่งที่ SIT ทดสอบไว้ · ค่าที่กรอกทุกบรรทัดถูกเขียนลงฐานข้อมูลจริงของปีงบประมาณ 2027 เสร็จแล้วต้องแก้ทั้ง 4 ช่องกลับเป็นค่าที่ฝ่ายต้องการใช้จริง | N14: แถวทดสอบ 10IT013000 / 6211100110 · ช่องทดสอบหลัก = May · ช่องทศนิยม = Jun, Jul, Aug (เดิม 0 ทั้ง 4 ช่อง) · บรรทัด1: พิมพ์ 146 → ช่อง 100 / ข้อความ 'กรอก 146 · ระบบปรับเป็น 100 (ปัดเศษเป็นหลักร้อย)' / รวมทั้งปี 135,600.00 · ข้อความหายเองภายใน 7 วินาที (ตรวจซ้ำแล้วไม่เหลือ) · บรรทัด2: พิมพ์ 30 → ช่อง 0 / 'กรอก 30 ซึ่งต่ำกว่า 100 · ระบบบันทึกเป็น 0 (กรอกได้ตั้งแต่ 100 ขึ้นไป)' / รวม 135,500.00 · บรรทัด3: พิมพ์ 999999999999 (12 หลัก) → ช่อง 100,000,000 / 'กรอก 999,999,999,999 ซึ่งเกินเพดาน 100 ล้านต่อช่อง · ระบบบันทึกเป็น 100,000,000' / รวม 100,135,500.00 · ไม่มีสัญลักษณ์ infinity ทั้งในช่องและยอดรวม · บรรทัด4: ยอดตั้งต้นของบรรทัดที่ 4 (อ่านสด) = 100,135,500.00 · พิมพ์ 33333.33 ลง Jun, Jul, Aug → ทั้ง 3 ช่องได้ 3,333,300 (ข้อความ 'กรอก 3,333,333 · ระบบปรับเป็น 3,333,300 (ปัดเศษเป็นหลักร้อย)' ยืนยันว่าตัดจุดทิ้ง) · ยอดหลังของบรรทัดที่ 4 = 110,135,400.00 · ผลต่าง = 9,999,900.00 พอดี · บรรทัด5: พิมพ์ abc ต่อท้าย แล้ว @#$ ต่อท้าย → ช่องคง 100000000 ไม่เปลี่ยน ไม่มีข้อความ · บรรทัด6: ลบค่าเดิมแล้วพิมพ์ -5000 → ช่อง 5000 (เครื่องหมายลบถูกตัด) ไม่มีข้อความ / รวม 10,140,400.00 · ข้อ10: คืนค่าทั้ง 4 ช่องเป็น 0 แล้ว | O14: Pass | R14: Pornthip | S14: 46274 | T14: [AI pre-run 09/09/2026] ผ่านครบทั้ง 6 บรรทัดและ Expected ข้อ 1-9 · ข้อความแจ้งเตือนขึ้นทุกบรรทัดที่มีการปัดค่า (1, 2, 3, 4) และเงียบในบรรทัด 5, 6 ตามที่ Expected ระบุ · การจับเวลา 6 วินาที: automation ตรวจที่ 7 วินาทีแล้วข้อความหายไปแล้ว ไม่ได้จับเวลาละเอียดกว่านั้น
... A50: W7 | B50: 48 | C50: 48 | D50: UAT-48 | E50: Email Alert / Notification | F50: Data & Analytic | H50: กด `Reject` แล้วผู้ส่งได้รับอีเมลแจ้งพร้อมเหตุผลที่ผู้อนุมัติพิมพ์ไว้ครบถ้วน | I50: High | J50: เคสนี้เป็นการ **ตรวจอีเมลที่เกิดจากการกด Reject ในเคส UAT-38** ไม่ใช่การตีกลับรอบใหม่ · สิ่งที่ต้องมีคือ เคส UAT-38 กด `Reject` ไปแล้วพร้อมเหตุผลตามช่อง Test Data และอีเมลฉบับนั้นยังอยู่ในกล่องจดหมายของผู้ส่ง — เมื่อมาถึงลำดับการรันนี้ สถานะของฝ่าย Data & Analytic เดินหน้าไปจากตอนนั้นแล้ว จึงไม่ต้องเป็น `Pending · Step 1 (Direct manager)` อีก และไม่ถือเป็น Fail · ระบบเปิดใช้งานการส่งอีเมลจริง · ผู้ทดสอบเปิดกล่องจดหมายของผู้ส่ง (พรทิพย์ pornthipp@chememan.com) ได้ · ห้ามกด `Reject` ซ้ำเพื่อสร้างอีเมลฉบับใหม่ และเคสนี้ต้องทำก่อนเคส UAT-47 / UAT-40 เพราะเมื่อสถานะเป็น `Approved` แล้วจะตีกลับไม่ได้อีก · **กล่องจดหมายจะมีอีเมลหัวข้อ "ถูกตีกลับ งบประมาณของฝ่าย Data & Analytic ปีงบประมาณ 2027" อยู่ 2 ฉบับที่หัวข้อเหมือนกันทุกตัวอักษร** ฉบับหนึ่งเกิดจากเคส UAT-38 (ตอนนี้) อีกฉบับเกิดจากเคส UAT-41 ที่ตีกลับซ้ำภายหลัง — แยกได้จากเวลาเท่านั้น ให้เทียบเวลาที่อีเมลเข้ากับเวลาที่จดไว้ตอนกด `Confirm Reject` ในเคส UAT-38 แล้วเลือกฉบับที่เข้า **ก่อน** (ตรงกับเวลานั้น) มาใช้ในเคสนี้ | K50: 1. ทำเคสนี้ไปพร้อมกับเคส UAT-38: เมื่อ UAT-38 กดปุ่ม `Reject` พิมพ์เหตุผลตามช่อง Test Data ลงในกล่อง `Reject reason (required)` และกด `Confirm Reject` เรียบร้อยแล้ว ให้ทำข้อถัดไปต่อทันที — เป็นการตีกลับครั้งเดียวกัน ไม่ใช่รอบใหม่ ถ้าตีกลับไปแล้วก่อนหน้านี้ ห้ามตีกลับซ้ำ ให้ใช้เหตุผลเดิมที่จดไว้ในเคส UAT-38 เป็นตัวเทียบ 2. เปิดกล่องจดหมายของผู้ส่ง (พรทิพย์ pornthipp@chememan.com) หาอีเมลหัวข้อ "ถูกตีกลับ งบประมาณของฝ่าย Data & Analytic ปีงบประมาณ 2027" — ถ้าเจอ 2 ฉบับ ให้เทียบเวลาที่แต่ละฉบับเข้ากับเวลาที่จดไว้ตอนกด `Confirm Reject` ในเคส UAT-38 แล้วเลือกฉบับที่เข้า **ก่อน** (ตรงกับเวลานั้นที่สุด) มาใช้ต่อในขั้นตอนถัดไป 3. เทียบเหตุผลที่แสดงในอีเมลฉบับที่เลือก กับข้อความที่จดไว้ในช่อง Actual Result ของเคส UAT-38 ทีละตัวอักษร 4. ตรวจช่อง cc ของอีเมลฉบับนั้น 5. คลิกลิงก์ในอีเมลสำหรับแก้ไขและส่งใหม่ แล้วดูว่าเปิดหน้างบของฝ่ายและปีใด | L50: เหตุผลที่ใช้เทียบ = **เหตุผลจริงที่พิมพ์ไว้ในเคส UAT-38** (ผู้ทดสอบจดไว้ในช่อง Actual Result ของ UAT-38 แล้ว) ไม่ใช่ข้อความตายตัว — **ห้ามเทียบกับคำว่า "ตัวเลขหมวด X ผิด"** เพราะไม่มีการพิมพ์คำนั้นจริงในรอบนี้ · เวลาที่ใช้แยกอีเมล 2 ฉบับ = เวลาที่จดไว้ตอนกด `Confirm Reject` ในเคส UAT-38 (ฉบับที่เข้าก่อน ใช้ในเคสนี้) เทียบกับเวลาที่จดไว้ในเคส UAT-41 (ฉบับที่เข้าทีหลัง ไม่ใช้ในเคสนี้) · ฝ่าย Data & Analytic · ปีงบประมาณ 2027 | M50: ผู้ส่ง (พรทิพย์) ได้รับอีเมลหัวข้อ "ถูกตีกลับ งบประมาณของฝ่าย Data & Analytic ปีงบประมาณ 2027" (ฉบับที่เวลาเข้าใกล้เคียงกับเวลาที่บันทึกไว้ตอนกด `Confirm Reject` ในเคส UAT-38 มากที่สุด) · เนื้อหาแสดงเหตุผลตรงกันทุกตัวอักษรกับ **เหตุผลจริงที่ผู้ทดสอบจดไว้ในช่อง Actual Result ของเคส UAT-38** (ไม่ใช่ข้อความตายตัวที่เขียนไว้ในเอกสารนี้) · สำเนา (cc) ถึงผู้อนุมัติขั้นที่ 1 และ cmanpowerbi@chememan.com · มีลิงก์สำหรับแก้ไขและส่งใหม่ และลิงก์เปิดเข้าหน้างบของฝ่าย Data & Analytic ปีที่ถูกต้อง — หมายเหตุสำคัญ — ต้องรันก่อนเคส UAT-40 / UAT-47 เพราะสถานะ `Approved` ย้อนกลับไม่ได้ ตีกลับหลังจากนั้นไม่ได้อีก · ใช้การกด `Reject` ชุดเดียวกับ UAT-38 ไม่ต้องตีกลับซ้ำ · อีเมลส่งจริงถึงกล่องจดหมายของพรทิพย์ ให้แจ้งเจ้าตัวล่วงหน้าว่าเป็นการทดสอบ | N50: เมล 'ถูกตีกลับ งบประมาณของฝ่าย Data & Analytic ปีงบประมาณ 2027' มี 2 ฉบับตามคาด: 02:58 (ตีกลับโดยลัดดาวัลย์ใน UAT-38 กด ~02:58 — ฉบับที่เคสนี้ใช้) และ 03:12 (ตีกลับโดยนิภาพรใน UAT-41 กด 03:11) แยกกันด้วยเวลาที่จดไว้ · เปิดฉบับเต็ม 03:12: ผู้ส่ง CMAN_PowerBI · To Pornthip Phermsaphiran · Cc Laddawan Kearnoi; CMAN_PowerBI · ตาราง ฝ่าย Data & Analytic / ปีงบประมาณ 2027 (หน้าจอ: Year 2026) / สถานะ 'ถูกตีกลับ' / เหตุผล 'ขอทบทวนตัวเลขใหม่ (UAT Round 1)' ตรงกับที่พิมพ์ทุกตัวอักษร · ลิงก์ 'คลิกที่นี่เพื่อแก้ไขและส่งใหม่' · อักษรไทยครบ | O50: Pass | R50: Pornthip | S50: 46274 | T50: [AI pre-run 09/09/2026] ผ่าน · ฉบับ 02:58 ของเคสนี้เองไม่ได้เปิดดูเนื้อหา แต่เป็น template เดียวกับ 03:12 ที่ตรวจแล้ว และเหตุผล 'UAT Round 1 — ขอทบทวนตัวเลขหมวดค่าเดินทางใหม่' ถูกพิมพ์โดย AI ตรงกับ UAT-38 · cc มีสำเนาเก็บ cmanpowerbi ครบ (ข้อกังวลเรื่องสำเนาหายตกไป) · ไทม์ไลน์เมลจริงจากรายการกล่องจดหมาย CMAN_PowerBI (cc ทุกฉบับ): 02:36 รอ D&A · 02:45 รอ SD · 02:49 รอ SD · 02:51 ตีกลับ SD · 02:58 ตีกลับ D&A · 03:01 รอ D&A · 03:08 รอ D&A · 03:12 ตีกลับ D&A · 03:17 รอ D&A · 03:18 รอ D&A · 03:19 รอ D&A · 03:22 ได้รับการอนุมัติ D&A · 14:26 รอ SD · 14:27 ตีกลับ SD (retest) · 📧 อ้างอิงอีเมล (ทุกฉบับผู้ส่ง = CMAN_PowerBI cmanpowerbi@chememan.com · วันที่ = พุธ 9 ก.ย. 2026 · ชื่อ jakkaritw ไม่อยู่ทั้ง To/CC จึงต้องเปิดกล่อง cmanpowerbi หรือกล่องผู้รับ) — Wed 2:58 AM — ถูกตีกลับ (Data & Analytic) → pornthipp · cc laddawank (ฉบับที่เคสนี้ใช้; อย่าสับกับ Wed 3:12 AM ซึ่งเป็นของ UAT-41)
A51: W7 | B51: 53 | C51: 49 | D51: UAT-49 | E51: Email Alert / Notification | F51: Data & Analytic | H51: ตรวจเนื้อหาอีเมลแจ้งเตือน 1 ฉบับเป็น checklist 8 ข้อ และเปิดอ่านบนมือถืออีก 1 ครั้ง | I51: High | J51: ได้รับอีเมลแจ้งเตือนจากระบบมาแล้วอย่างน้อย 1 ฉบับ แนะนำให้ใช้ฉบับ "ได้รับการอนุมัติ" ที่เกิดจากเคส UAT-47 ข้อ 3 · ผู้ทดสอบล็อกอินเข้าระบบได้เพื่อทดสอบลิงก์ในอีเมล · มีโทรศัพท์มือถือที่เปิดกล่องจดหมายเดียวกันได้ (ข้อนี้ SIT ค้างไว้ยังไม่เคยทำ) | K51: 1. เปิดอีเมลฉบับที่เลือกบนคอมพิวเตอร์ แล้วจดลงช่อง Actual Result ว่าใช้อีเมลฉบับใด (หัวข้อ + วันเวลาที่ได้รับ) 2. ดูชื่อและอีเมลของผู้ส่ง 3. ดูช่อง To และ CC ของอีเมลฉบับนั้น 4. อ่านหัวข้ออีเมล แล้วเทียบกับรูปแบบที่คาดไว้ในช่อง Expected Result 5. อ่านเนื้อความทั้งฉบับ เทียบ ฝ่าย / ปีงบประมาณ / สถานะ กับงบที่ทำจริง 6. คลิกลิงก์ `คลิกที่นี่เพื่อดูรายละเอียด` ในอีเมล แล้วดูว่าเปิดหน้าใด 7. ตรวจตัวอักษรไทยทั้งหัวข้อและเนื้อหาว่าไม่มี ??? หรืออักขระเพี้ยน 8. ตรวจว่าอีเมลอยู่ในกล่อง Inbox ไม่ตกไปโฟลเดอร์ Junk/Spam 9. เทียบปีงบประมาณที่ระบุในอีเมลกับปีที่หน้าจอระบบแสดง 10. เปิดอีเมลฉบับเดียวกันบนมือถืออีก 1 ครั้ง แล้วตรวจการแสดงผลภาษาไทยซ้ำบนมือถือ | L51: อีเมลที่ใช้ตรวจ: "ได้รับการอนุมัติ งบประมาณของฝ่าย Data & Analytic ปีงบประมาณ 2027" · ฝ่าย = Data & Analytic · ปีในอีเมล = 2027 · ปีบนหน้าจอ = `Year 2026` · ผู้กรอกงบ = pornthipp@chememan.com · ผู้อนุมัติขั้นที่ 1 = laddawank@chememan.com | M51: ⚠ เคสรวม (merged) — 1 แถวแต่มีหลายข้อที่ต้องตรวจ อ่านให้ครบทุกข้อก่อนตัดสิน Pass 1) ผู้ส่งแสดงเป็น CMAN_PowerBI (อีเมล cmanpowerbi@chememan.com) 2) To = pornthipp@chememan.com (ผู้กรอกงบ) · CC = laddawank@chememan.com (ผู้อนุมัติขั้นที่ 1) และ cmanpowerbi@chememan.com (สำเนาเก็บของระบบ) · ผู้อนุมัติขั้นที่ 2 และ 3 ไม่ได้รับสำเนา 3) หัวข้อ = "ได้รับการอนุมัติ งบประมาณของฝ่าย Data & Analytic ปีงบประมาณ 2027" ชื่อฝ่ายและปีตรงกับงบที่ทำจริง 4) เนื้อหาระบุครบ: ฝ่าย = Data & Analytic, ปีงบประมาณ = 2027, สถานะ = "อนุมัติครบทุกขั้นแล้ว" 5) ลิงก์ `คลิกที่นี่เพื่อดูรายละเอียด` เปิดหน้างบของฝ่ายและปีเดียวกับที่ระบุไว้ในอีเมลทันที คือฝ่าย Data & Analytic และปีที่หน้าจอแสดงว่า `Year 2026` โดยไม่ต้องเลือกฝ่ายหรือปีเองอีก ไม่ขึ้นข้อความแสดงข้อผิดพลาด และไม่ใช่หน้าเปล่า 6) ตัวอักษรไทยแสดงครบถูกต้อง ไม่มี ??? หรืออักขระเพี้ยน ทั้งบนคอมพิวเตอร์และบนมือถือ 7) อีเมลเข้ากล่อง Inbox ตามปกติภายในเวลาที่ยอมรับได้ ไม่ตกไปโฟลเดอร์ Junk/Spam 8) ปีงบประมาณในอีเมลคือ 2027 ขณะที่หน้าจอแสดง `Year 2026` — จับคู่ปีถูกต้องตามที่ออกแบบ ไม่สลับปีผิด — หมายเหตุสำคัญ — เคสเดียวแต่มี 8 ข้อที่ต้องตรวจแยกกัน (ยุบมาจาก SIT 8 เคส) อ่านช่อง Expected Result ให้ครบทั้ง 8 ข้อก่อน mark Pass · SIT ตรวจข้อ 6 เฉพาะบนคอมพิวเตอร์และค้างการเปิดบนมือถือไว้ รอบนี้ต้องเปิดบนมือถืออย่างน้อย 1 ครั้ง · ถ้าจำเป็นต้องใช้อีเมลฉบับอื่นที่ไม่ใช่ "ได้รับการอนุมัติ" ให้จดหัวข้อฉบับที่ใช้จริงลงช่อง Actual Result แล้วเทียบ To/CC และหัวข้อตามฉบับนั้น เพราะข้อ 2 กับข้อ 3 เขียนตามฉบับ "ได้รับการอนุมัติ" | N51: ข้อ 5 (ลิงก์ในอีเมล): ระบบสร้างลิงก์รูปแบบ /?dept=Data%20%26%20Analytic&year=2026 (ปีบนลิงก์ = ปีหน้าจอ) · เปิดลิงก์นี้ในนาม Pornthip → หน้าเปิดที่ฝ่าย 'Data & Analytic' ปี 'Year 2026' ถูกเลือกทันที ตาราง 10 แถวโหลดครบ สถานะ 'Approved' ไม่มีข้อความผิดพลาด ไม่ใช่หน้าเปล่า · ข้อ 8: อีเมลระบุ 'ปีงบประมาณ 2027 (หน้าจอ: Year 2026)' ตามภาพกล่องจดหมาย Laddawan ที่ jakkaritw เปิดดู — จับคู่ปีถูกต้อง · จากภาพเดียวกัน: ผู้ส่ง CMAN_PowerBI, To ผู้อนุมัติ, Cc CMAN_PowerBI, หัวข้อ 'รอการอนุมัติ งบประมาณของฝ่าย Data & Analytic ปีงบประมาณ 2027', ตัวอักษรไทยครบ ไม่มี ??? (บนคอมพิวเตอร์) | R51: Pornthip | S51: 46274 | T51: [AI pre-run 09/09/2026] สถานะจาก AI: Partial — ข้อ 1-6, 8 ผ่าน; เหลือข้อ 7 (Junk) และเปิดบนมือถือ · คนตรวจฉบับ 'ได้รับการอนุมัติ … 2027' ที่ Pornthip ได้ ~03:21: To pornthipp / Cc laddawank + cmanpowerbi, สถานะ 'อนุมัติครบทุกขั้นแล้ว', Inbox ไม่ใช่ Junk, และเปิดบนมือถือ 1 ครั้ง (ข้อค้างจาก SIT) · ยังไม่มีหลักฐานเมลฉบับ 'ได้รับการอนุมัติ' 03:21 จริง (To/CC/เนื้อหา/Junk/มือถือ) · [ตรวจอีเมล 09/09 บ่าย] หลักฐานจริงที่มี = ภาพหน้าจอ Outlook ของ jakkaritw เมื่อเช้า (เห็นเมล 02:36, 02:45, 02:49, 02:51, 02:58, 03:01) · เมลช่วง 03:06–03:21 ยังไม่มีใครเห็นจริง · การเข้า shared mailbox cmanpowerbi@chememan.com ผ่าน Claude ตอบ 404/FORBIDDEN = บัญชี jakkaritw ไม่มีสิทธิ์ Full Access ต้องขอจาก Exchange admin หรือให้เจ้าตัวเปิดกล่องเอง · รายงานจาก session อื่นที่สรุปว่า 'ผ่าน' เป็นการเทียบกับตารางคาดการณ์ ไม่ใช่หลักฐานจากกล่องจดหมาย จึงไม่เปลี่ยน Status · [ภาพอีเมลจริงจาก jakkaritw 09/09 ~16:00] จากฉบับ 'ได้รับการอนุมัติ': ข้อ 1 ผู้ส่ง CMAN_PowerBI ✓ · ข้อ 2 To pornthipp, CC laddawank + cmanpowerbi ✓ · ข้อ 3 หัวข้อ 'ได้รับการอนุมัติ งบประมาณของฝ่าย Data & Analytic ปีงบประมาณ 2027' ✓ · ข้อ 4 ฝ่าย / 2027 / 'อนุมัติครบทุกขั้นแล้ว' ✓ · ข้อ 6 อักษรไทยครบบนคอมพิวเตอร์ ✓ · ข้อ 8 '2027 (หน้าจอ: Year 2026)' ✓ · ข้อ 5 ลิงก์ทดสอบแล้วโดย AI ✓ · เหลือข้อ 7 (Inbox ไม่ตก Junk — ภาพเปิดจากกล่องจดหมายปกติ น่าจะผ่าน ให้เจ้าตัวยืนยัน) และเปิดบนมือถือ 1 ครั้ง · [รายการกล่องจดหมาย CMAN_PowerBI (cc ทุกฉบับ) ภาพจาก jakkaritw 09/09 ~16:10] ฉบับ 'ได้รับการอนุมัติ' อยู่ในรายการกล่องจดหมายปกติ 03:22 (Inbox ไม่ตก Junk สำหรับกล่อง cmanpowerbi) · ยังเหลือเปิดบนมือถือ 1 ครั้ง และยืนยัน Inbox ของพรทิพย์เอง · 📧 อ้างอิงอีเมล (ทุกฉบับผู้ส่ง = CMAN_PowerBI cmanpowerbi@chememan.com · วันที่ = พุธ 9 ก.ย. 2026 · ชื่อ jakkaritw ไม่อยู่ทั้ง To/CC จึงต้องเปิดกล่อง cmanpowerbi หรือกล่องผู้รับ) — Wed 3:22 AM — ได้รับการอนุมัติ (Data & Analytic) → pornthipp · cc laddawank, cmanpowerbi (ฉบับที่เคสนี้ใช้)
A52: W7 | B52: 49 | C52: 50 | D52: UAT-50 | E52: Email Alert / Notification | F52: Data & Analytic | H52: อีเมลยังเป็นภาษาไทยขณะที่หน้าจออนุมัติเป็นภาษาอังกฤษ — ให้ผู้ใช้ตัดสินและบันทึกคำตอบลงช่อง Remarks | I52: Medium | J52: ผ่านเคส UAT-46 / UAT-47 / UAT-48 มาแล้วอย่างน้อยหนึ่งเคส จึงมีอีเมลของระบบอยู่ในกล่องจดหมายให้เปิดเทียบได้ · เปิดหน้าจออนุมัติของระบบดูควบคู่กันได้ในเวลาเดียวกัน · มีผู้ใช้ที่มีสิทธิ์ตัดสินเรื่องภาษาของอีเมลอยู่ด้วยเพื่อให้คำตอบ | K52: 1. เปิดหน้าจออนุมัติในระบบด้วยบัญชีผู้อนุมัติ แล้วจดข้อความภาษาอังกฤษที่เห็นจริงบนจอในตอนนั้น เช่น ปุ่ม `Approve` และ `Reject` · ป้ายสถานะ `Pending · Step 1 (Direct manager)` · กล่องเหตุผล `Reject reason (required)` กับปุ่ม `Confirm Reject` · และป้ายในตัวเลือกฝ่าย `Pending` (ส่วนป้าย `Approved` และ `Draft — not submitted` เป็นป้ายสถานะของงบที่อนุมัติครบแล้ว และงบที่ยังไม่ส่ง จะเห็นก็ต่อเมื่องบอยู่ในสถานะนั้น ไม่ต้องตามหาบนหน้าจอนี้) 2. เปิดอีเมลที่ระบบส่งออกจากเคส UAT-46 / UAT-47 / UAT-48 แล้วจดว่าหัวข้อและเนื้อหาเป็นภาษาใด 3. เทียบคำที่ใช้เรียกสถานะเดียวกันทั้งสองฝั่ง เช่น หน้าจอ `Pending` ↔ อีเมล "รอการอนุมัติ" · หน้าจอ `Approved` ↔ อีเมล "อนุมัติครบทุกขั้นแล้ว" · หน้าจอ `Reject` ↔ อีเมล "ถูกตีกลับ" 4. ให้ผู้ใช้ตัดสินว่ารับสภาพ "หน้าจอเป็นภาษาอังกฤษ + อีเมลเป็นภาษาไทย" นี้ได้ หรือต้องแปลอีเมลเป็นภาษาอังกฤษด้วย 5. บันทึกคำตอบของผู้ใช้ลงช่อง Remarks ของแถวนี้ เช่น "รับได้ ไม่ต้องแก้" หรือ "ต้องแปลอีเมลเป็นภาษาอังกฤษด้วย" | L52: ข้อความบนหน้าจอ (ภาษาอังกฤษ): `Approve` / `Reject` / `Pending · Step 1 (Direct manager)` / `Reject reason (required)` / `Confirm Reject` / `Approved` / `Draft — not submitted` / ป้ายในตัวเลือกฝ่าย `Pending` · ข้อความในอีเมล (ภาษาไทย): "รอการอนุมัติ" / "ถูกตีกลับ" / "ได้รับการอนุมัติ" / "อนุมัติครบทุกขั้นแล้ว" | M52: ยืนยันได้ว่าหน้าจออนุมัติแสดงเป็นภาษาอังกฤษ ขณะที่อีเมลแจ้งเตือนทุกฉบับยังเป็นภาษาไทยทั้งหัวข้อและเนื้อหา — นี่คือสภาพปัจจุบันของระบบที่ต้องบันทึกไว้ ไม่ใช่ข้อผิดพลาดที่ยืนยันแล้ว · เคสนี้ตัดสินจากคำตอบของผู้ใช้ ไม่ใช่จากพฤติกรรมของระบบ: ถ้าผู้ใช้รับสภาพนี้ได้ ให้ mark Pass พร้อมบันทึกคำตอบลงช่อง Remarks · ถ้าผู้ใช้ต้องการให้แปลอีเมลเป็นภาษาอังกฤษด้วย ให้บันทึกเป็นคำขอเปลี่ยนแปลงในแถวของแท็บ `4. Defects` และอ้างเลขที่ไว้ในช่อง Defect ID — หมายเหตุสำคัญ — เป็นเคสให้ผู้ใช้ตัดสิน (decision case) ต้องได้คำตอบเป็นลายลักษณ์อักษรในช่อง Remarks ก่อนปิดรอบ UAT — ถ้าปล่อยว่างไว้ถือว่าเคสยังไม่จบ · ไม่มีเคสใดใน SIT ที่เคยเทียบภาษาของหน้าจอกับภาษาของอีเมล จึงไม่มีผลเดิมให้อ้างอิง | N52: หน้าจออนุมัติเป็นภาษาอังกฤษ: ปุ่ม Approve / Reject · chip 'Pending · Step 1 (Direct manager)' / 'Pending · Step 2 (นิภาพร ทองกิ่ง (Senior Associate))' / 'Rejected' / 'Approved' · กล่อง 'REJECT REASON (REQUIRED)' + 'Confirm Reject' · ป้าย 'Pending' ในตัวเลือกฝ่าย · ข้อความ 'Submitted — locked for editing until it is rejected' · อีเมลทุกฉบับเป็นภาษาไทยทั้งหัวข้อและเนื้อหา: 'รอการอนุมัติ …' / 'ถูกตีกลับ …' / 'ได้รับการอนุมัติ …' สถานะ 'รอการอนุมัติจากท่าน' / 'ถูกตีกลับ' / 'อนุมัติครบทุกขั้นแล้ว' · คู่คำเดียวกัน: Pending ↔ รอการอนุมัติ, Rejected ↔ ถูกตีกลับ, Approved ↔ ได้รับการอนุมัติ | O52: Pass | R52: ไม่ระบุชื่อในเคส (ต้องมีคนเปิดทั้งจอ+อีเมลเทียบกัน — สันนิษฐาน Pornthip) | S52: 46274 | T52: [AI pre-run 09/09/2026] jakkaritw ตัดสิน 2026-09-09: รับสภาพ 'หน้าจออังกฤษ / อีเมลไทย' ได้ → Pass ไม่เปิดคำขอเปลี่ยนแปลง · 📧 อ้างอิงอีเมล (ทุกฉบับผู้ส่ง = CMAN_PowerBI cmanpowerbi@chememan.com · วันที่ = พุธ 9 ก.ย. 2026 · ชื่อ jakkaritw ไม่อยู่ทั้ง To/CC จึงต้องเปิดกล่อง cmanpowerbi หรือกล่องผู้รับ) — ใช้อีเมลฉบับใดก็ได้ข้างต้นเป็นตัวอย่าง — ประเด็นคือหัวข้อ/เนื้อหาเป็นภาษาไทยขณะหน้าจอเป็นอังกฤษ
A53: W8 | B53: 54 | C53: 51 | D53: UAT-51 | E53: Business Rules & UI | F53: - | H53: กวาดตาดูหน้าจอทั้งระบบรอบเดียว ทั้ง Chrome และ Edge — ชุดสีของบริษัท ข้อความไทย และยอดตัวเลขยาว ๆ | I53: Medium | J53: ล็อกอินเป็น Pornthip ได้ทั้งบน Google Chrome และ Microsoft Edge (เวอร์ชันล่าสุดทั้งคู่) · ระบบรองรับความละเอียดขั้นต่ำ 1366×768 บนเดสก์ท็อปหรือโน้ตบุ๊ก ไม่รองรับมือถือในเวอร์ชันนี้ · ในตารางต้องมีข้อมูลที่กรอกไว้แล้วจากระลอก W2–W4 และมีอย่างน้อย 1 ช่องที่ยอดถึงหลักล้าน เพื่อให้เห็นตัวเลขยาวจริง · เลือกฝ่ายที่มีชื่อภาษาไทยยาวไว้ดูอย่างน้อย 1 ฝ่าย | K53: 1. เปิด URL ของระบบด้วย Chrome ที่ความละเอียด 1920×1080 ล็อกอินเป็น Pornthip แล้วเลือกฝ่าย Data & Analytic ปีบนจอ Year 2026 2. กวาดตาดูส่วนบนของหน้าจอ: โลโก้บริษัทบนแถบบนสุด · แถบผู้ใช้ (ชื่อ อีเมล ป้าย role สายงาน ชื่อฝ่าย จำนวน Cost Center จำนวน GL) · แถบเครื่องมือ (ตัวเลือกปี ตัวเลือกฝ่าย ปุ่ม `+ เพิ่ม Transaction` ปุ่ม `แนบไฟล์`) · คำอธิบาย 3 ชั้น (legend) 3. ดูตารางหลักทั้ง 2 ฝั่ง (ฝั่งผลิต/ต้นทุน 5xxx และฝั่งบริหาร/ขาย SG&A 6xxx): หัวตาราง ชื่อ Cost Center ชื่อ GL ชื่อกลุ่ม GL ยอดรายเดือนทั้ง 12 เดือน ยอด `รวมทั้งปี` ยอดรวมย่อยต่อกลุ่ม GL และยอดรวมใหญ่ 4. เลื่อนลงไปดูแถบอนุมัติที่อยู่ใต้ตาราง: ป้ายสถานะ ข้อความข้างป้าย และปุ่มเท่าที่แสดงอยู่ในสถานะนั้น 5. เปิดฟอร์มย่อย 1 ฟอร์ม (เช่น Entertainment) และเปิด Trip Manager 1 หน้าต่าง แล้วดูสีพื้น สีตัวอักษร ปุ่ม และข้อความในนั้น 6. เปิดกล่อง `แนบไฟล์` 1 ครั้ง แล้วดูรายการไฟล์และปุ่มในกล่อง 7. หาช่องที่มียอดยาวที่สุด (หลักล้าน เช่น 3,333,300) ทั้งในช่องรายเดือน ช่อง `รวมทั้งปี` แถวยอดรวมย่อยต่อกลุ่ม GL และแถวยอดรวมใหญ่ แล้วตรวจว่าตัวเลขไม่ทับกันและไม่ถูกตัดหาย 8. ย่อหน้าต่างเบราว์เซอร์เป็น 1366×768 แล้วดูซ้ำตั้งแต่ข้อ 2 ถึงข้อ 7 9. โหลดหน้าใหม่ (refresh) 1 ครั้ง แล้วตรวจว่าชื่อฝ่ายภาษาไทยและชื่อ GL ยาว ๆ ยังแสดงถูกต้อง 10. ทำซ้ำข้อ 1 ถึงข้อ 9 ทั้งหมดอีกรอบบน Microsoft Edge 11. (**ทำที่ตำแหน่งเคส UAT-37 ตามลำดับการรัน ไม่ใช่ตอนนี้** — ถึงตำแหน่งของเคสนี้ ฝ่าย Data & Analytic จะเป็น `Approved` แล้ว และฝ่าย Solution Delivery ก็ถูกตีกลับคืนสถานะ `Rejected` ไปแล้วตั้งแต่เคส UAT-43 จึงไม่มีฝ่ายใดค้างอยู่ในสถานะ `Pending` ให้ดู) ขอให้ผู้อนุมัติ (Laddawan) เปิดหน้าจอฝ่ายที่ค้างอนุมัติของตน 1 ครั้ง แล้วดูสีและความชัดของปุ่ม `Approve` / `Reject` กับป้ายสถานะ แล้วกลับมาบันทึกผลลงช่อง Actual Result ของเคสนี้ (UAT-51) — ไม่ต้องกดปุ่มใด ๆ ในเคสนี้ 12. จุดใดที่อ่านยาก สีกลืนกัน ตัวอักษรหาย หรือตัวเลขทับกัน ให้ถ่ายภาพหน้าจอเก็บไว้ และจดว่าพบบนเบราว์เซอร์ใดและที่ความละเอียดเท่าใด | L53: เบราว์เซอร์: Google Chrome (เวอร์ชันล่าสุด) และ Microsoft Edge (เวอร์ชันล่าสุด) · ความละเอียด: 1920×1080 และ 1366×768 · ฝ่าย: Data & Analytic · ปีบนจอ: Year 2026 · ต้องมีอย่างน้อย 1 ช่องที่ยอดถึงหลักล้าน (เช่น 3,333,300) | M53: ⚠ เคสรวม (merged) — 1 แถวแต่มีหลายข้อที่ต้องตรวจ อ่านให้ครบทุกข้อก่อนตัดสิน Pass 1) ชุดสีเป็นสีของบริษัทจริง — เขียว `#00805e` และกรมท่า `#1b3564` — โลโก้และตัวอักษรบนพื้นสีอ่านออกชัดทุกจุด ทั้งในตาราง ปุ่ม ป้ายสถานะ แถบอนุมัติ ฟอร์มย่อย และปุ่ม `Approve` / `Reject` บนหน้าจอของผู้อนุมัติ ไม่มีจุดที่สีตัวอักษรกลืนไปกับสีพื้นจนอ่านไม่ออก 2) ข้อความภาษาไทยแสดงครบ อ่านออก ไม่มีตัวอักษรกลายเป็นกล่องสี่เหลี่ยม · ช่องที่ข้อความยาวเกินแสดง "…" และเห็นข้อความเต็มเมื่อชี้เมาส์ · หลังโหลดหน้าใหม่ชื่อฝ่ายภาษาไทยยังแสดงถูกต้อง 3) ยอดตัวเลขยาว ๆ ไม่ทับกัน — อ่านได้ครบทุกหลัก ไม่ล้นออกนอกช่อง และไม่ถูกตัวเลขของช่องข้าง ๆ บัง ทั้งในช่องรายเดือน ช่อง `รวมทั้งปี` แถวยอดรวมย่อยต่อกลุ่ม GL และแถวยอดรวมใหญ่ (ข้อนี้คือคำตอบของคำถามค้างจาก SIT: "ยอดยาวๆจะทับกันไหม??") 4) Chrome และ Edge แสดงผลเหมือนกัน · ที่ 1366×768 ตารางเลื่อนแนวนอนได้โดยคอลัมน์ Cost Center และ GL ตรึงอยู่ซ้าย หัวตารางตรึงด้านบน · ปุ่ม `แนบไฟล์` แถบอนุมัติ และปุ่มเท่าที่ระบบแสดงตามสถานะของฝ่ายในขณะนั้น (เช่น `Submit` เมื่อฝ่ายยังแก้ไขได้ หรือ `Approve` / `Reject` เมื่อเป็นผู้อนุมัติ) ยังมองเห็นครบและกดถึงได้ ไม่ถูกบัง — หมายเหตุสำคัญ — เคสนี้เป็น 1 แถวแต่มี 4 ข้อที่ต้องตรวจ ต้องอ่าน Expected Result ให้ครบทั้ง 4 ข้อก่อนกด Pass · การตรวจบน Microsoft Edge เป็นข้อค้างจาก SIT (ผู้ทดสอบเดิมบันทึกไว้ว่า "ยังต้องให้คนตรวจบน Edge") รอบนี้ต้องมีคนเปิดบน Edge จริง ไม่ใช่เดาว่าเหมือนกัน · ชุดสีของบริษัทเพิ่งเปลี่ยนหลังปิดรอบ SIT ผู้ทดสอบเดิมจึงเห็นสีเขียวคนละเฉดกับที่เห็นตอนนี้ อย่าใช้ภาพหน้าจอเก่าเป็นเกณฑ์เทียบ · ถ้าพบจุดที่อ่านยากหรือตัวเลขทับกัน ให้เปิดแถวใหม่ในชีต `4. Defects` แล้วแนบภาพหน้าจอไปด้วย · เคสนี้ทำหลังระลอก W6 ฝ่ายที่ใช้ดูอาจอยู่ในสถานะ `Approved` แล้ว ปุ่ม `Submit` จะไม่ปรากฏ ซึ่งถูกต้องตามสถานะ ไม่ใช่ข้อผิดพลาด ให้ตรวจเฉพาะปุ่มที่มีจริงในสถานะนั้น | N53: รันครบบนทั้ง 2 เบราว์เซอร์ × 2 ความละเอียด (grid, subform Entertainment, Trip Manager, กล่องแนบไฟล์, refresh) ผลเหมือนกันทุกชุด: · ตัวเลขยาวสุด 135,500.00 ไม่มีช่องไหนล้น (overflow cells = 0) · ตารางเลื่อนแนวนอนในกรอบของตัวเอง body ไม่มี horizontal scroll · หัวตารางตรึงบน คอลัมน์ Cost Center/GL ตรึงซ้าย (sticky = true ทั้งคู่) · อักษรไทยครบ ไม่มี ??? หลัง refresh · · contrast (WCAG AA ต้อง ≥ 4.5 ข้อความปกติ / ≥ 3 ข้อความใหญ่): ข้อความหลักผ่านสบาย — โลโก้บนแถบเขียว 4.94, ป้าย role 9.18, ชื่อฝ่าย/GL/ตัวเลข 17.04, หัวเดือน 7.83, ยอดรวม 14.56 · พบ 'ต่ำกว่า AA เล็กน้อย' 3 จุดที่เป็นข้อความรอง สีเทา #727781 บนขาว = 4.49 (อีเมลผู้ใช้, legend 'Approved'/'Pending', label ในฟอร์มย่อย/Trip/หัวตารางแนบไฟล์) — ห่างเกณฑ์ 0.01 · และปุ่มฟอร์มย่อยตอนล็อก '🔒 ดูรายละเอียด' สีทอง #c1952e บนพื้นครีม = 2.52–2.63 (เป็นสไตล์ disabled โดยตั้งใจ) | O53: Pass | R53: Pornthip → Laddawan | S53: 46274 | T53: [AI pre-run 09/09/2026] AI ไม่ตัดสินเรื่องสายตา · ข้อเสนอ (ไม่บล็อก): ยกสีเทารอง #727781 ให้เข้มขึ้นอีกนิดให้ถึง 4.5 และเพิ่มน้ำหนักปุ่มล็อก 🔒 ถ้าอยากให้อ่านง่ายขึ้น — เป็นงานปรับสีเล็ก ไม่กระทบข้อมูล · ยอดหลักล้าน (3,333,300) ไม่มีในข้อมูลรอบนี้ ถ้าจะพิสูจน์ข้อ 7 เต็มต้องพิมพ์ในฝ่ายที่ยังแก้ได้ · ผู้ทดสอบดูภาพแล้วติ๊ก Pass ได้ถ้าอ่านออกชัด · jakkaritw ตัดสิน 2026-09-09: รับได้ → Pass
A54: W8 | B54: 50 | C54: 52 | D54: UAT-52 | E54: Business Rules & UI | F54: - | H54: ข้อความแจ้งข้อผิดพลาดบอกสาเหตุและวิธีแก้ ไม่แสดงศัพท์เทคนิคหรือ stack trace ให้ผู้ใช้เห็น | I54: Medium | J54: มีฝ่ายที่ส่งขออนุมัติไปแล้วอย่างน้อย 1 ฝ่าย — ตามลำดับการรันคือฝ่าย Data & Analytic ที่สถานะบนจอเป็น `Pending · Step 1 (Direct manager)` และ **ยังไม่ถึงขั้น `Approved`** · ขั้นตอนที่ 1, 3, 4 และ 5 ทำที่ตำแหน่งนี้ตามลำดับการรัน เพราะต้องใช้ฝ่ายที่ส่งขออนุมัติไปแล้วแต่ยัง **ไม่** เป็น `Approved` — เคสนี้จึงถูกจัดให้รัน **ก่อนเคส UAT-40** · แต่ **ขั้นตอนที่ 2 (จำนวนวันเดินทางติดลบ) ทำที่ตำแหน่งนี้ไม่ได้** เพราะระบบล็อกการแก้ไขทั้งฝ่ายตั้งแต่ตอนกด `Submit` ไม่ใช่ตอน `Approved` — พอสถานะเป็น `Pending` แล้ว Trip Manager จะเปิดขึ้นมาเป็นแบบอ่านอย่างเดียว (หัวกล่องขึ้นคำว่า `🔒 อ่านอย่างเดียว (แก้ไม่ได้)` ช่องกรอกทุกช่องถูกปิด และปุ่ม `บันทึก & ลงบัญชี` หายไปทั้งปุ่ม) จึงพิมพ์ค่า -3 ไม่ได้เลย · ขั้นตอนที่ 2 ต้อง **ทำทันทีหลัง UAT-26 ก่อนเริ่ม UAT-32** ซึ่งเป็นช่วงที่ฝ่ายยังเป็น `Draft — not submitted` และทริปที่สร้างไว้ในระลอก W3 ยังแก้ไขได้ · ผู้ทดสอบสามารถปิดและเปิด Wi-Fi ของเครื่องตัวเองได้ | K54: 1. เลือกฝ่ายที่ส่งขออนุมัติไปแล้ว จากนั้นลองแก้ยอดในช่องเดือนหนึ่ง และลองกด `+ เพิ่ม Transaction` · จดข้อความที่ระบบแสดงลงช่อง Actual Result แบบคำต่อคำ 2. (**ทำทันทีหลัง UAT-26 ก่อนเริ่ม UAT-32** — ตอนนั้นฝ่ายยังเป็น `Draft — not submitted` และทริปของระลอก W3 ยังแก้ไขได้ · ถ้ารอมาทำตอนถึงลำดับการรันของเคสนี้จะทำไม่ได้ เพราะฝ่ายถูกล็อกตั้งแต่กด `Submit` ในเคส UAT-32 แล้ว Trip Manager จะเปิดเป็นแบบอ่านอย่างเดียวและปุ่ม `บันทึก & ลงบัญชี` หายไปทั้งปุ่ม) เปิด Trip Manager ของทริปที่ยังแก้ไขได้ กรอกจำนวนวันเดินทางเป็นค่าติดลบ (เช่น -3) แล้วกด `บันทึก & ลงบัญชี` · จดข้อความที่ระบบแสดง แล้วกลับมาบันทึกผลลงช่อง Actual Result ของเคสนี้ 3. ปิด Wi-Fi ของเครื่อง แล้วพิมพ์ยอดลงช่องเดือนหนึ่งและคลิกออกจากช่องเพื่อให้ระบบพยายามบันทึก · จดข้อความที่ระบบแสดง แล้วเปิด Wi-Fi กลับและโหลดหน้าใหม่ 4. อ่านข้อความบนจอทุกข้อความที่เจอในขั้นตอนที่ 1 ถึง 3 แล้วตอบ 2 คำถามนี้ต่อข้อความ: (ก) บอกสาเหตุหรือไม่ (ข) บอกว่าต้องทำอะไรต่อหรือไม่ 5. ถ้าระหว่างระลอก W1 ถึง W7 เคยเจอข้อความแจ้งข้อผิดพลาดที่อ่านไม่รู้เรื่อง ให้นำมาจดรวมไว้ในเคสนี้ด้วย พร้อมระบุว่าเจอที่หน้าจอไหน | L54: ฝ่ายที่สถานะเป็น `Pending · Step 1 (Direct manager)` · จำนวนวันเดินทาง = -3 · ปิด Wi-Fi ชั่วคราว 1 ครั้งขณะกดบันทึก | M54: 1) ในฝ่ายที่ส่งขออนุมัติไปแล้ว ช่องยอดเป็นแบบอ่านอย่างเดียว พิมพ์แก้ไม่ได้ตั้งแต่แรก (ไม่จำเป็นต้องมีข้อความแจ้ง ถือว่าถูกต้อง) · ส่วนการกด `+ เพิ่ม Transaction` ต้องถูกปฏิเสธพร้อมข้อความภาษาไทยที่บอกว่าฝ่ายนี้ถูกล็อกเพราะส่งขออนุมัติแล้ว และบอกสิ่งที่ต้องทำต่อ 2) (ตรวจตอนฝ่ายยังแก้ไขได้) การกรอกจำนวนวันเดินทางเป็นค่าติดลบถูกกันตั้งแต่ช่องกรอก: พิมพ์ `-3` ช่องจะเปลี่ยนเป็น `3` ทันที (เครื่องหมายลบถูกตัดทิ้ง) โดยไม่มีข้อความแจ้ง — jakkaritw ตัดสิน 2026-09-09 ว่ายอมรับได้ ถือว่าผ่านเมื่อระบบไม่ยอมรับค่าติดลบ · ผู้ทดสอบต้องตรวจค่าในช่องอีกครั้งก่อนกด `บันทึก & ลงบัญชี` 3) ตอนไม่มีอินเทอร์เน็ต ระบบแสดงข้อความภาษาไทยที่บอกสาเหตุ (บันทึกไม่สำเร็จ / ติดต่อระบบไม่ได้) และบอกสิ่งที่ต้องทำต่อ ไม่เงียบหายไปเฉย ๆ 4) ทุกข้อความในขั้นตอนที่ 1 ถึง 3 ไม่มี stack trace ชื่อไฟล์ .py หรือคำสั่ง SQL ปรากฏบนหน้าจอ · รายละเอียดภาษาอังกฤษที่ต่อท้ายข้อความให้บันทึกเป็นข้อสังเกต ไม่ถือเป็น Fail 5) ข้อความในส่วนของการอนุมัติที่เป็นภาษาอังกฤษ (เช่น `Submitted — locked for editing until it is rejected`) เป็นการออกแบบไว้แบบนั้นหลังแปลหน้าจออนุมัติเป็นภาษาอังกฤษ ไม่ใช่ข้อผิดพลาด — หมายเหตุสำคัญ — กรณี "เปิด 2 แท็บแล้วแก้แถวเดียวกันพร้อมกัน" ที่ SIT เคยมีอยู่ ถูกตัดออกจากรอบนี้แล้ว — jakkaritw ตัดสินเมื่อ 2026-08-20 ว่าผ่าน เพราะตัวเลขอัปเดตให้ทันทีอยู่แล้ว โอกาสพลาดน้อยมาก จึงไม่ต้องทดสอบซ้ำ · ตามลำดับการรัน เคสนี้ถูกวางไว้ **ก่อนเคส UAT-40 โดยตั้งใจ** เพราะขั้นตอนที่ 1 ต้องใช้ฝ่ายที่ส่งขออนุมัติแล้วแต่ยัง **ไม่** เป็น `Approved` — ห้ามเลื่อนเคสนี้ไปทำหลัง UAT-40 · แต่ **ขั้นตอนที่ 2 (จำนวนวันเดินทางติดลบ) ทำตรงตำแหน่งนี้ไม่ได้** เพราะระบบล็อกการแก้ไขทั้งฝ่ายตั้งแต่ตอนกด `Submit` ไม่ใช่ตอน `Approved` — สถานะ `Pending` ทั้ง 3 ขั้นล็อกเท่ากับ `Approved` ทุกประการ ทำให้ Trip Manager เปิดเป็นแบบอ่านอย่างเดียวและไม่มีปุ่ม `บันทึก & ลงบัญชี` ให้กด · **หยุด — ต้องย้อนกลับไปทำขั้นตอนที่ 2 ทำทันทีหลัง UAT-26 ก่อนเริ่ม UAT-32** ซึ่งเป็นช่วงเดียวในรอบทดสอบที่ทริปยังแก้ไขได้ ถ้าไม่ทำตามป้ายนี้ การทดสอบจำนวนวันเดินทางติดลบจะหายไปจากรอบนี้ทั้งรอบ · ถ้าถึงตอนนั้นแล้วไม่มีทริปที่แก้ไขได้เหลืออยู่จริง ห้ามข้ามเงียบ ๆ ให้บันทึกเป็น Blocked พร้อมเหตุผลลงช่อง Remarks แล้วแจ้งหัวหน้าทีมทดสอบทันที (ฝ่าย Solution Delivery ไม่มีแถวงบให้ใช้แทน และปีอื่นนอกจากปีงบประมาณ 2027 ยังไม่เปิดให้กรอก) · ขั้นตอนที่ 3 ให้ปิด Wi-Fi ของเครื่องตัวเองเท่านั้น อย่าไปแตะอุปกรณ์เครือข่ายของสำนักงาน | N54: ข้อ 1 (ฝ่าย Data & Analytic สถานะ Pending · Step 1): โหลดหน้าใหม่แล้วช่องเดือนทั้งหมดเป็นตัวหนังสืออ่านอย่างเดียว ไม่มีช่องพิมพ์เลย (0 ช่อง) ปุ่มฟอร์มย่อยเปลี่ยนเป็น '🔒 ดูรายละเอียด' tooltip 'อ่านอย่างเดียว — แก้ไม่ได้ในสถานะนี้' ปุ่มลบแถวหายทั้งหมด · ปุ่ม '+ เพิ่ม Transaction' ยังกดได้ → ฟอร์มเลือก Cost Center / GL เปิดขึ้น เลือก 10IT013000 + 6210900060 — ค่าไปรษณีย์ กด บันทึก → ข้อความสีแดงในฟอร์ม (คำต่อคำ): 'ฝ่าย "Data & Analytic" อยู่ระหว่างอนุมัติหรืออนุมัติแล้ว ไม่สามารถเพิ่มรายการใหม่ในฝ่ายนี้ได้ในสถานะนี้' แถวไม่ถูกเพิ่ม (ยังคง 10 แถว) กด ยกเลิก ปิดฟอร์มได้ · ข้อ 4 สำหรับข้อความนี้: (ก) บอกสาเหตุ = ใช่ (ข) บอกสิ่งที่ต้องทำต่อ = ไม่ชัด (ไม่บอกว่าต้องรอตีกลับหรือรอรอบถัดไป) · ไม่มี stack trace / .py / SQL · ข้อ 2 (ทำตอนฝ่ายกลับเป็น Rejected หลัง UAT-41 ทริปแก้ได้อีกครั้ง): เปิด Trip Manager ผ่านปุ่มฟอร์มย่อย GL 6210400020 เห็นทริป 52 และ 53 (วันเดินทาง 5 / 5) · พิมพ์ -3 ลงช่องวันเดินทางของทริป 52 → ช่องรับค่าเป็น 3 ทันที (เครื่องหมายลบถูกตัดทิ้ง) ไม่มีข้อความแจ้งใด ๆ · กด บันทึก & ลงบัญชี → บันทึกสำเร็จเงียบ ๆ ด้วยค่า 3 วัน (AI แก้กลับเป็น 5 และบันทึกซ้ำแล้ว ยอด per diem กลับเป็น 13,200 / 13,200 รวม 26,400 และรวมทั้งหมด 415,900.00 เท่าเดิม ตรวจหลังโหลดหน้าใหม่) · ข้อ 3 (จำลองตัดเครือข่ายเฉพาะ browser ทดสอบ ไม่แตะ Wi-Fi เครื่อง): พิมพ์ 4,100 ลงช่อง ก.ค. ของ GL 6210400999 (เดิม 4,000) คลิกออก → แถบข้อความ 'เชื่อมต่อเซิร์ฟเวอร์ไม่ได้ กรุณาตรวจสอบอินเทอร์เน็ต' ค่าที่พิมพ์ยังค้างบนจอ · คืนเครือข่ายแล้วโหลดหน้าใหม่ → ค่ากลับเป็น 4,000 (ไม่ถูกบันทึกระหว่างไม่มีเน็ต) · ข้อ 4: ข้อความข้อ 3 บอกสาเหตุ = ใช่ บอกสิ่งที่ต้องทำ = ใช่ (ตรวจอินเทอร์เน็ต) · ทุกข้อความไม่มี stack trace / .py / SQL · ข้อ 5: ตลอด W1-W7 ไม่พบข้อความแจ้งข้อผิดพลาดที่อ่านไม่รู้เรื่อง | O54: Pass | R54: Pornthip | S54: 46274 | T54: [AI pre-run 09/09/2026] ผ่านทุกข้อ · ข้อ 2: ระบบกันค่าติดลบตั้งแต่ช่องกรอก (พิมพ์ -3 ได้ 3) ไม่มีข้อความ — jakkaritw ตัดสิน 2026-09-09 ว่ายอมรับได้ แก้ Expected ข้อ 2 ให้ตรงระบบแล้ว (AI แก้ทริป 52 กลับเป็น 5 วันแล้ว ยอดเท่าเดิม) · ปุ่ม + เพิ่ม Transaction ยังกดได้ในฝ่ายที่ล็อก (ปฏิเสธตอนบันทึกด้วยข้อความไทย) — jakkaritw ตัดสิน 2026-09-09 ว่ายอมรับได้ ไม่เปิด defect · ข้อ 3 ใช้การบล็อก API ใน browser ทดสอบแทนปิด Wi-Fi จริง รอบคนควรปิด Wi-Fi ซ้ำ 1 ครั้ง
A55: W8 | B55: 32 | C55: 53 | D55: UAT-53 | E55: Business Rules & UI | F55: Data & Analytic | H55: เงินต้องไม่หายเงียบ — ลบทริปแล้วยอดที่กรอกไว้ในช่อง 6210400999 ของ Cost Center และปีเดียวกันต้องยังอยู่ครบ | I55: High | J55: ฝ่าย Data & Analytic ปีบนจอ Year 2026 ยังอยู่ในสถานะที่แก้ไขได้ (`Draft — not submitted` หรือถูกตีกลับแล้ว) — ถ้าส่งขออนุมัติไปแล้วจะกรอกยอดไม่ได้ ต้องทำเคสนี้ก่อนกด Submit หรือหลังจากถูกตีกลับ · มีทริปที่สร้างไว้ในระลอก W3 อย่างน้อย 1 ใบ อยู่ใน Cost Center และปีเดียวกันกับที่จะใช้ทดสอบ · ผู้ทดสอบเป็น Filler ของ Cost Center นั้น | K55: 1. เลือกฝ่าย Data & Analytic ปีบนจอ Year 2026 แล้วใช้ตัวกรองคอลัมน์ Cost Center เลือก Cost Center ที่จะใช้ทดสอบ (เช่น 10IT011300) 2. กด `+ เพิ่ม Transaction` เลือก Cost Center นั้นและ GL `6210400999` (ค่าใช้จ่ายเดินทางอื่น) แล้วเพิ่มแถวใหม่ · ถ้ามีแถวนี้อยู่แล้วให้ใช้แถวเดิม 3. กรอกยอด 5,000 ลงช่องเดือนกรกฎาคมของแถวนั้น แล้วคลิกออกจากช่องเพื่อให้ระบบบันทึกอัตโนมัติ 4. จดยอดที่ระบบแสดงในช่องนั้น (5,000 เป็นหลักร้อยอยู่แล้ว ระบบจึงไม่ปัดค่า) และจดยอด `รวมทั้งปี` ของแถวนั้น ลงช่อง Actual Result (นี่คือค่าตั้งต้น "ก่อนลบทริป") 5. เปิด Trip Manager ของ Cost Center และปีเดียวกัน โดยกดปุ่ม `แก้ไขผ่านฟอร์มย่อย` จากแถว GL เบี้ยเลี้ยง ค่าพาหนะ หรือค่าที่พัก ที่มีทริปอยู่ 6. เลือกทริปที่สร้างไว้ในระลอก W3 แล้วกดลบทริป และยืนยันที่กล่อง `ลบทริปนี้ทั้งหมด?` 7. ปิดหน้าต่าง Trip Manager กลับมาที่ตารางหลัก แล้วโหลดหน้าใหม่ (refresh) 8. ดูแถว GL `6210400999` ของ Cost Center เดิมอีกครั้ง จดยอดในช่องเดือนกรกฎาคมและยอด `รวมทั้งปี` ที่เห็น ลงช่อง Actual Result (นี่คือค่า "หลังลบทริป") แล้วเทียบกับค่าที่จดไว้ในขั้นตอนที่ 4 | L55: Cost Center: 10IT011300 (หรือ Cost Center อื่นในฝ่าย Data & Analytic) · GL: 6210400999 (ค่าใช้จ่ายเดินทางอื่น) · ยอดทดสอบ: 5,000 ในเดือนกรกฎาคม · ทริปที่จะลบ: ทริปที่สร้างขึ้นเองในระลอก W3 ของ Cost Center และปีเดียวกัน | M55: 1) ยอดในช่องเดือนกรกฎาคมของแถว GL `6210400999` ยังเป็นค่าเดิมทุกบาท ไม่หายไปและไม่กลายเป็น 0 2) แถว GL `6210400999` ยังคงอยู่ในตาราง ไม่ถูกลบทิ้งไปพร้อมทริป 3) ยอด `รวมทั้งปี` ของแถวนั้นเท่ากับก่อนลบทริป 4) ยอดที่จดไว้ในขั้นตอนที่ 4 และขั้นตอนที่ 8 เป็นตัวเลขเดียวกัน 5) ยอดที่เปลี่ยนได้มีเฉพาะ 3 GL ของทริป (เบี้ยเลี้ยง ค่าพาหนะ ค่าที่พัก) ที่ถูกลบไปพร้อมทริปเท่านั้น — หมายเหตุสำคัญ — เคสนี้คือการยืนยันการแก้บั๊ก "เงินหายเงียบ ๆ" — ตอนที่ยังเป็นบั๊ก เงินหายโดยไม่มีข้อความแจ้ง ไม่มี log และไม่มีอีเมล ผู้ใช้จึงไม่มีทางรู้ตัว ถ้าตัวเลขในขั้นตอนที่ 8 ไม่เท่ากับขั้นตอนที่ 4 ให้เปิด Defect ระดับ Blocker ทันที · การลบทริปย้อนกลับไม่ได้ ให้ลบเฉพาะทริปที่สร้างขึ้นเองในรอบ UAT นี้เท่านั้น ห้ามลบทริปของคนอื่น · ต้องทำเคสนี้ตอนที่ฝ่ายยังแก้ไขได้ ถ้าฝ่ายถูกล็อกจากการ Submit ไปแล้ว ให้เลื่อนไปทำหลังจากถูกตีกลับ หรือทำก่อนเริ่มระลอก W5 | N55: ใช้ Cost Center 10IT013000 (ที่มีทริปของระลอก W3) · เพิ่มแถว 6210400999 ผ่านฟอร์ม + เพิ่ม Transaction · กรอก ก.ค. 5000 → ช่องแสดง 5000 รวมทั้งปี 5,000.00 (ค่าตั้งต้น) · เปิด Trip Manager จากแถวค่าพาหนะ ลบทริป existing-54 (Thailand มิ.ย. 3 วัน ที่สร้างใน UAT-25) ยืนยันที่กล่อง 'ลบทริปนี้ทั้งหมด?' · ปิดหน้าต่าง refresh → แถว 6210400999 ยังอยู่ ก.ค. = 5000 รวมทั้งปี 5,000.00 เท่าเดิมทุกบาท · ยอดที่เปลี่ยนมีเฉพาะ GL ของทริป: เบี้ยเลี้ยง มิ.ย. 750.00 → — (รวมปี 27,150 → 26,400) · ค่าพาหนะ/ค่าที่พักไม่เปลี่ยน (ทริปที่ลบไม่มียอด 2 แถวนี้) · GL อื่นทั้งหมดเท่าเดิม (135,500 / 38,000 / 101,000 / 32,000 / 36,000) | O55: Pass | R55: ไม่ระบุชื่อในเคส (ต้องเป็น Filler ของ Cost Center นั้น = Pornthip) | S55: 46274 | T55: [AI pre-run 09/09/2026] ผ่าน Expected ข้อ 1-5 ทุกข้อ · บั๊ก 'เงินหายเงียบ' ไม่เกิดซ้ำ · เบี่ยงเบนจาก Test Data: ใช้ CC 10IT013000 แทน 10IT011300 เพราะทริปทั้งหมดอยู่ที่ 10IT013000 และเคสบังคับว่าต้องเป็น CC เดียวกับทริป (10IT011300 ไม่มีทริป) · ทริปที่เหลือ: existing-52 (พ.ค.) และ existing-53 (เม.ย.)
A56: W8 | B56: 33 | C56: 54 | D56: UAT-54 | E56: Business Rules & UI | F56: Data & Analytic | H56: เปลี่ยนอัตราแลกเปลี่ยนแล้วฟอร์มย่อยแสดงยอดใหม่ทันที แต่ตารางหลักยังเป็นยอดเดิมจนกดบันทึกซ้ำ — ผู้ใช้เซ็นรับทราบว่ายอมรับพฤติกรรมนี้ | I56: Medium | J56: มีทริป **ต่างประเทศ** ที่สร้างไว้ในระลอก W3 อย่างน้อย 1 ใบ (เช่น ปลายทาง Singapore) เพราะทริปในประเทศคิดเป็นเงินบาทอยู่แล้ว จึงไม่ได้รับผลจากอัตราแลกเปลี่ยน · ฝ่าย Data & Analytic ปีบนจอ Year 2026 ยังอยู่ในสถานะที่แก้ไขได้ เพราะขั้นตอนนี้ต้องกด `บันทึก & ลงบัญชี` ซ้ำ · ต้องมีผู้ดูแลระบบ (admin) ที่แก้อัตราแลกเปลี่ยนในไฟล์ master ได้ และพร้อมคืนค่าเดิมทันทีที่ทดสอบเสร็จ | K56: 1. เปิดทริปต่างประเทศใบเดิมขึ้นมา จดยอดเบี้ยเลี้ยงที่ฟอร์มย่อยแสดง และจดยอดของ 3 GL (เบี้ยเลี้ยง ค่าพาหนะ ค่าที่พัก) ที่ตารางหลักแสดง ลงช่อง Actual Result (ค่าตั้งต้น) 2. ขอให้ผู้ดูแลระบบแก้อัตราแลกเปลี่ยน USD ต่อ THB ใน master แล้วรอให้ระบบรับค่าใหม่ · จดทั้งค่าเดิมและค่าใหม่ไว้ · ถ้าเปิดฟอร์มย่อยในขั้นตอนถัดไปแล้วยอดยังไม่เปลี่ยน ให้ถามผู้ดูแลระบบก่อนว่าค่าใหม่เข้าระบบแล้วหรือยัง อย่าเพิ่งบันทึกเป็น Fail 3. เปิดทริปใบเดิมขึ้นมาใหม่ ดูยอดเบี้ยเลี้ยงในฟอร์มย่อย แล้วจดยอดที่เห็น 4. ปิดฟอร์มโดย **ยังไม่กด** `บันทึก & ลงบัญชี` แล้วดูยอดของ 3 GL ในตารางหลัก จดยอดที่เห็น (เทียบเฉพาะแถวเบี้ยเลี้ยงเป็นหลัก อีก 2 แถวเป็นยอดที่กรอกเองจึงต้องเท่าเดิม) 5. เปิดทริปใบเดิมอีกครั้ง แล้วกด `บันทึก & ลงบัญชี` หนึ่งครั้ง ปิดหน้าต่าง แล้วดูยอดของ 3 GL ในตารางหลักอีกครั้ง จดยอดที่เห็น 6. ขอให้ผู้ดูแลระบบคืนค่าอัตราแลกเปลี่ยนเดิม แล้วเปิดทริปกด `บันทึก & ลงบัญชี` ซ้ำอีกครั้ง เพื่อให้ยอดในตารางกลับไปเป็นค่าตั้งต้นของขั้นตอนที่ 1 7. อธิบายพฤติกรรมนี้ให้ผู้ใช้ฟัง แล้วให้ผู้ใช้บันทึกคำตอบลงช่อง Remarks ว่า "รับทราบและยอมรับพฤติกรรมนี้" หรือ "ไม่ยอมรับ ต้องการให้ระบบอัปเดตยอดในตารางให้อัตโนมัติ" | L56: ทริปต่างประเทศ 1 ใบ (เช่น ปลายทาง Singapore) · อัตราแลกเปลี่ยน USD ต่อ THB: จดค่าเดิม ___ และค่าที่ใช้ทดสอบ ___ · ยอดเบี้ยเลี้ยงในฟอร์มย่อย: ก่อนเปลี่ยน ___ / หลังเปลี่ยน ___ · ยอดเบี้ยเลี้ยงในตารางหลัก: ก่อนเปลี่ยน ___ / หลังเปลี่ยนแต่ยังไม่บันทึกซ้ำ ___ / หลังกดบันทึกซ้ำ ___ · ยอดค่าพาหนะและค่าที่พักในตารางหลัก (ต้องเท่าเดิมตลอดเคส): ___ | M56: 1) ฟอร์มย่อย (Trip Manager) แสดงยอดเบี้ยเลี้ยงที่คำนวณด้วยอัตราแลกเปลี่ยนใหม่ทันทีที่เปิดขึ้นมา โดยไม่ต้องทำอะไรเพิ่ม 2) ตารางหลักยังแสดงยอดเบี้ยเลี้ยงเดิมที่บันทึกไว้ตอนกดบันทึกครั้งก่อน จนกว่าจะกด `บันทึก & ลงบัญชี` ซ้ำ — ยอดสองที่ไม่ตรงกันชั่วคราวในช่วงนี้เป็นพฤติกรรมที่ตั้งใจไว้ ไม่ใช่ข้อผิดพลาด 3) หลังกด `บันทึก & ลงบัญชี` ยอด **เบี้ยเลี้ยง** ในตารางหลักเปลี่ยนเป็นยอดใหม่และตรงกับที่ฟอร์มย่อยแสดง · ยอด **ค่าพาหนะ** และ **ค่าที่พัก** ไม่เปลี่ยน เพราะเป็นยอดที่ผู้ใช้กรอกเองเป็นเงินบาท ไม่ได้คำนวณจากอัตราแลกเปลี่ยน — สองแถวนี้เท่าเดิมถือว่าถูกต้อง ไม่ใช่ Fail 4) หลังคืนอัตราแลกเปลี่ยนเดิมและกดบันทึกซ้ำ ยอดเบี้ยเลี้ยงในตารางหลักกลับไปเท่ากับค่าตั้งต้นที่จดไว้ในขั้นตอนที่ 1 ทุกบาท และยอดค่าพาหนะกับค่าที่พักยังเท่าเดิมตลอดทั้งเคส 5) ผู้ใช้บันทึกคำตอบลงช่อง Remarks แล้ว — ตอบว่ายอมรับหรือไม่ยอมรับก็ได้ ทั้งสองคำตอบไม่ทำให้เคสนี้เป็น Fail ถ้าตอบว่าไม่ยอมรับ ให้บันทึกเป็นความต้องการเพิ่มเติม ไม่ใช่ defect — หมายเหตุสำคัญ — พฤติกรรมนี้ตัดสินไปแล้วเมื่อ 2026-08-21 ว่าจะไม่แก้ (jakkaritw) — **ห้ามแจ้งเป็น defect** จุดประสงค์ของเคสนี้คือให้ผู้ใช้รับรู้และเซ็นรับทราบก่อนใช้งานจริง ไม่ใช่การหาข้อบกพร่อง · การแก้อัตราแลกเปลี่ยนคือการแก้ข้อมูล master จริงบนระบบจริง ให้ผู้ดูแลระบบเป็นคนทำเท่านั้น จดค่าเดิมไว้ก่อน และคืนค่าเดิมทันทีที่ทดสอบเสร็จ · ถ้าทีมตัดสินว่าไม่ควรแตะ master จริงในรอบนี้ ให้ข้ามขั้นตอนที่ 2 ถึง 6 แล้วทำเฉพาะขั้นตอนที่ 7 (อธิบายพฤติกรรมให้ผู้ใช้ฟังแล้วบันทึกคำตอบ) พร้อมระบุใน Actual Result ว่าเลือกใช้ทางเลือกใด · ต้องทำเคสนี้ก่อนที่ฝ่ายจะถูกอนุมัติครบ 3 ขั้น เพราะต้องกด `บันทึก & ลงบัญชี` ซ้ำได้ | N56: ค่าตั้งต้น (ขั้นตอนที่ 1) จดไว้แล้ว: ทริปต่างประเทศ Singapore 5 วัน (ทริป existing-53 เดือน เม.ย. และ existing-52 เดือน พ.ค.) เบี้ยเลี้ยงในฟอร์มย่อย = 13,200.00 ต่อทริป · ตารางหลัก 6210400010 เม.ย. 13,200.00 / พ.ค. 13,200.00 · 6210400020 พ.ค. 18,000.00 · 6210400030 พ.ค. 25,000.00 · อัตราแลกเปลี่ยนใน master ปี 2027 = 33.0000 USD/THB (dbo.master_currency_rate) · ขั้นตอนที่ 2-6 (ให้ admin แก้อัตราแลกเปลี่ยนในไฟล์ master จริงแล้วคืนค่า) AI ไม่ทำ เพราะเป็นการแก้ master ของทั้งบริษัทบนระบบจริง | O56: Pass | R56: Pornthip | S56: 46274 | T56: [AI pre-run 09/09/2026] ทางเลือกตาม note ของเคส: ข้ามขั้นตอน 2-6 ทำเฉพาะขั้นตอนที่ 7 · ต้องให้คนอธิบายพฤติกรรม (ฟอร์มย่อยคำนวณใหม่ทันที แต่ตารางหลักคงยอดเดิมจนกดบันทึกซ้ำ — ตัดสินแล้ว 2026-08-21 ว่าไม่แก้) แล้วให้ผู้ใช้เขียนใน Remarks ว่ารับทราบหรือไม่ · ถ้าทีมตัดสินใจทดสอบจริง admin ต้องแก้ค่า 33.0000 แล้วคืนค่าทันที · jakkaritw ตัดสิน 2026-09-09: อ่านเข้าใจ / ยอมรับได้ → Pass

Sheet 3. Summary
B2: UAT Test Execution — Summary · Round 1 · FY2027
B3: สรุปผลอัตโนมัติจากแท็บ “2. Test Cases” (ไม่ต้องกรอกเอง) · ทุกสูตรนับช่วงแถวจริง 3–56
B5: Result | C5: Count
B6: Total test cases | C6: =COUNTA('2. Test Cases'!$D$3:$D$56)
B7: Pass | C7: =COUNTIF('2. Test Cases'!$O$3:$O$56,"Pass")
B8: Fail | C8: =COUNTIF('2. Test Cases'!$O$3:$O$56,"Fail")
B9: Blocked | C9: =COUNTIF('2. Test Cases'!$O$3:$O$56,"Blocked")
B10: Not Run (ยังไม่ได้ทดสอบ) | C10: =C6-C7-C8-C9-C11
B11: N/A | C11: =COUNTIF('2. Test Cases'!$O$3:$O$56,"N/A")
B12: Pass Rate (Pass / Executed) | C12: =IFERROR(COUNTIF('2. Test Cases'!$O$3:$O$56,"Pass")/(COUNTIF('2. Test Cases'!$O$3:$O$56,"Pass")+COUNTIF('2. Test Cases'!$O$3:$O$56,"Fail")+COUNTIF('2. Test Cases'!$O$3:$O$56,"Blocked")),"-")
B14: Breakdown by Module | G14: Breakdown by Wave | M14: Breakdown by Department
B15: Module | C15: Total | D15: Pass | E15: Fail | G15: Wave | H15: ชื่อระลอก | I15: Total | J15: Pass | K15: Fail | M15: Department | N15: Total | O15: Pass | P15: Fail
B16: Login / Authentication | C16: =COUNTIF('2. Test Cases'!$E$3:$E$56,"Login / Authentication") | D16: =COUNTIFS('2. Test Cases'!$E$3:$E$56,"Login / Authentication",'2. Test Cases'!$O$3:$O$56,"Pass") | E16: =COUNTIFS('2. Test Cases'!$E$3:$E$56,"Login / Authentication",'2. Test Cases'!$O$3:$O$56,"Fail") | G16: W1 | H16: เข้าระบบและสิทธิ์ที่มองเห็น | I16: =COUNTIF('2. Test Cases'!$A$3:$A$56,"W1") | J16: =COUNTIFS('2. Test Cases'!$A$3:$A$56,"W1",'2. Test Cases'!$O$3:$O$56,"Pass") | K16: =COUNTIFS('2. Test Cases'!$A$3:$A$56,"W1",'2. Test Cases'!$O$3:$O$56,"Fail") | M16: Data & Analytic | N16: =COUNTIF('2. Test Cases'!$F$3:$F$56,"Data & Analytic") | O16: =COUNTIFS('2. Test Cases'!$F$3:$F$56,"Data & Analytic",'2. Test Cases'!$O$3:$O$56,"Pass") | P16: =COUNTIFS('2. Test Cases'!$F$3:$F$56,"Data & Analytic",'2. Test Cases'!$O$3:$O$56,"Fail")
B17: Budget Entry (Filler) | C17: =COUNTIF('2. Test Cases'!$E$3:$E$56,"Budget Entry (Filler)") | D17: =COUNTIFS('2. Test Cases'!$E$3:$E$56,"Budget Entry (Filler)",'2. Test Cases'!$O$3:$O$56,"Pass") | E17: =COUNTIFS('2. Test Cases'!$E$3:$E$56,"Budget Entry (Filler)",'2. Test Cases'!$O$3:$O$56,"Fail") | G17: W2 | H17: กรอกงบในตารางหลัก | I17: =COUNTIF('2. Test Cases'!$A$3:$A$56,"W2") | J17: =COUNTIFS('2. Test Cases'!$A$3:$A$56,"W2",'2. Test Cases'!$O$3:$O$56,"Pass") | K17: =COUNTIFS('2. Test Cases'!$A$3:$A$56,"W2",'2. Test Cases'!$O$3:$O$56,"Fail") | M17: Solution Delivery | N17: =COUNTIF('2. Test Cases'!$F$3:$F$56,"Solution Delivery") | O17: =COUNTIFS('2. Test Cases'!$F$3:$F$56,"Solution Delivery",'2. Test Cases'!$O$3:$O$56,"Pass") | P17: =COUNTIFS('2. Test Cases'!$F$3:$F$56,"Solution Delivery",'2. Test Cases'!$O$3:$O$56,"Fail")
B18: Special GL Subform | C18: =COUNTIF('2. Test Cases'!$E$3:$E$56,"Special GL Subform") | D18: =COUNTIFS('2. Test Cases'!$E$3:$E$56,"Special GL Subform",'2. Test Cases'!$O$3:$O$56,"Pass") | E18: =COUNTIFS('2. Test Cases'!$E$3:$E$56,"Special GL Subform",'2. Test Cases'!$O$3:$O$56,"Fail") | G18: W3 | H18: ฟอร์มย่อยและทริปเดินทาง | I18: =COUNTIF('2. Test Cases'!$A$3:$A$56,"W3") | J18: =COUNTIFS('2. Test Cases'!$A$3:$A$56,"W3",'2. Test Cases'!$O$3:$O$56,"Pass") | K18: =COUNTIFS('2. Test Cases'!$A$3:$A$56,"W3",'2. Test Cases'!$O$3:$O$56,"Fail") | M18: ทั้งสองฝ่าย | N18: =COUNTIF('2. Test Cases'!$F$3:$F$56,"ทั้งสองฝ่าย") | O18: =COUNTIFS('2. Test Cases'!$F$3:$F$56,"ทั้งสองฝ่าย",'2. Test Cases'!$O$3:$O$56,"Pass") | P18: =COUNTIFS('2. Test Cases'!$F$3:$F$56,"ทั้งสองฝ่าย",'2. Test Cases'!$O$3:$O$56,"Fail")
B19: Attachments | C19: =COUNTIF('2. Test Cases'!$E$3:$E$56,"Attachments") | D19: =COUNTIFS('2. Test Cases'!$E$3:$E$56,"Attachments",'2. Test Cases'!$O$3:$O$56,"Pass") | E19: =COUNTIFS('2. Test Cases'!$E$3:$E$56,"Attachments",'2. Test Cases'!$O$3:$O$56,"Fail") | G19: W4 | H19: แนบเอกสาร | I19: =COUNTIF('2. Test Cases'!$A$3:$A$56,"W4") | J19: =COUNTIFS('2. Test Cases'!$A$3:$A$56,"W4",'2. Test Cases'!$O$3:$O$56,"Pass") | K19: =COUNTIFS('2. Test Cases'!$A$3:$A$56,"W4",'2. Test Cases'!$O$3:$O$56,"Fail") | M19: - | N19: =COUNTIF('2. Test Cases'!$F$3:$F$56,"-") | O19: =COUNTIFS('2. Test Cases'!$F$3:$F$56,"-",'2. Test Cases'!$O$3:$O$56,"Pass") | P19: =COUNTIFS('2. Test Cases'!$F$3:$F$56,"-",'2. Test Cases'!$O$3:$O$56,"Fail")
B20: Submission / Workflow | C20: =COUNTIF('2. Test Cases'!$E$3:$E$56,"Submission / Workflow") | D20: =COUNTIFS('2. Test Cases'!$E$3:$E$56,"Submission / Workflow",'2. Test Cases'!$O$3:$O$56,"Pass") | E20: =COUNTIFS('2. Test Cases'!$E$3:$E$56,"Submission / Workflow",'2. Test Cases'!$O$3:$O$56,"Fail") | G20: W5 | H20: ส่งขออนุมัติ | I20: =COUNTIF('2. Test Cases'!$A$3:$A$56,"W5") | J20: =COUNTIFS('2. Test Cases'!$A$3:$A$56,"W5",'2. Test Cases'!$O$3:$O$56,"Pass") | K20: =COUNTIFS('2. Test Cases'!$A$3:$A$56,"W5",'2. Test Cases'!$O$3:$O$56,"Fail") | M20: รวม / Total | N20: =SUM(N16:N19) | O20: =SUM(O16:O19) | P20: =SUM(P16:P19)
B21: Approval | C21: =COUNTIF('2. Test Cases'!$E$3:$E$56,"Approval") | D21: =COUNTIFS('2. Test Cases'!$E$3:$E$56,"Approval",'2. Test Cases'!$O$3:$O$56,"Pass") | E21: =COUNTIFS('2. Test Cases'!$E$3:$E$56,"Approval",'2. Test Cases'!$O$3:$O$56,"Fail") | G21: W6 | H21: อนุมัติ 3 ขั้น | I21: =COUNTIF('2. Test Cases'!$A$3:$A$56,"W6") | J21: =COUNTIFS('2. Test Cases'!$A$3:$A$56,"W6",'2. Test Cases'!$O$3:$O$56,"Pass") | K21: =COUNTIFS('2. Test Cases'!$A$3:$A$56,"W6",'2. Test Cases'!$O$3:$O$56,"Fail")
B22: Email Alert / Notification | C22: =COUNTIF('2. Test Cases'!$E$3:$E$56,"Email Alert / Notification") | D22: =COUNTIFS('2. Test Cases'!$E$3:$E$56,"Email Alert / Notification",'2. Test Cases'!$O$3:$O$56,"Pass") | E22: =COUNTIFS('2. Test Cases'!$E$3:$E$56,"Email Alert / Notification",'2. Test Cases'!$O$3:$O$56,"Fail") | G22: W7 | H22: อีเมลแจ้งเตือน | I22: =COUNTIF('2. Test Cases'!$A$3:$A$56,"W7") | J22: =COUNTIFS('2. Test Cases'!$A$3:$A$56,"W7",'2. Test Cases'!$O$3:$O$56,"Pass") | K22: =COUNTIFS('2. Test Cases'!$A$3:$A$56,"W7",'2. Test Cases'!$O$3:$O$56,"Fail")
B23: Business Rules & UI | C23: =COUNTIF('2. Test Cases'!$E$3:$E$56,"Business Rules & UI") | D23: =COUNTIFS('2. Test Cases'!$E$3:$E$56,"Business Rules & UI",'2. Test Cases'!$O$3:$O$56,"Pass") | E23: =COUNTIFS('2. Test Cases'!$E$3:$E$56,"Business Rules & UI",'2. Test Cases'!$O$3:$O$56,"Fail") | G23: W8 | H23: หน้าตาและกติกาที่ต้องยอมรับ | I23: =COUNTIF('2. Test Cases'!$A$3:$A$56,"W8") | J23: =COUNTIFS('2. Test Cases'!$A$3:$A$56,"W8",'2. Test Cases'!$O$3:$O$56,"Pass") | K23: =COUNTIFS('2. Test Cases'!$A$3:$A$56,"W8",'2. Test Cases'!$O$3:$O$56,"Fail")
B24: รวม / Total | C24: =SUM(C16:C23) | D24: =SUM(D16:D23) | E24: =SUM(E16:E23) | G24: รวม / Total | I24: =SUM(I16:I23) | J24: =SUM(J16:J23) | K24: =SUM(K16:K23)
B26: หมายเหตุ: ตัวเลขอัปเดตอัตโนมัติเมื่อกรอกคอลัมน์ Status ในแท็บ “2. Test Cases” · ช่วงข้อมูลจริง = แถวที่ 3 ถึง 56 · ไฟล์นี้ไม่มีแถวตัวอย่าง (ไม่มี TC-EX) · ช่อง Total ของทั้ง 3 ตารางต้องเท่ากับ Total test cases ด้านบน · แถว Not Run คำนวณจาก “Total ลบด้วย Pass + Fail + Blocked + N/A” จึงนับช่อง Status ที่ยังว่างให้เป็น Not Run โดยอัตโนมัติ (ไม่ต้องพิมพ์คำว่า Not Run เอง) และทำให้ห้าแถวบนรวมกันได้เท่ากับ Total เสมอ

Sheet 4. Defects
A1: Budget Web App — UAT Defect Log · เปิดแถวใหม่ทุกครั้งที่มีเคส Status = Fail แล้วนำเลข Defect ID ไปใส่ในคอลัมน์ Defect ID ของแท็บ “2. Test Cases”
A2: Defect ID | B2: UAT Case ID | C2: Department | D2: Title | E2: Severity | F2: Reported by | G2: Reported date | H2: Owner | I2: Status | J2: Fixed in | K2: Retest date | L2: Retest result | M2: Notes
A3: D-001
A4: D-002
A5: D-003
A6: D-004
A7: D-005
A8: D-006
A9: D-007
A10: D-008
A11: D-009
A12: D-010
A13: D-011
A14: D-012
... A44: Severity ของ defect ใช้ **ชุดค่าเดียวกับคอลัมน์ Severity ในแท็บ “2. Test Cases”** ยกมาใส่ได้ตรง ๆ ไม่ต้องแปลงค่า: Critical = ระบบใช้งานไม่ได้ / ข้อมูลเงินผิดพลาดร้ายแรง · High = ฟังก์ชันหลักเสีย · Medium = เสียแต่มีทางเลี่ยง · Low = ปัญหาเล็กน้อยหรือ UI (ไม่มีค่า `-` ในแท็บนี้ เพราะแถว defect เกิดขึ้นเฉพาะตอนมีเคส Fail) · Status: Open → In Progress → Fixed → Retested → Closed (หรือ Wont Fix ถ้าตัดสินว่าไม่แก้)

Sheet 5. AI Pre-Run
A1: AI pre-run บน production ผ่าน /sit/impersonate — 09/09/2026 00:54–03:26
A2: AI สวมสิทธิ์เป็นผู้ทดสอบตามคอลัมน์ Tester แล้วรันตาม Run Order · ผลอยู่ในช่องสีเหลืองของแท็บ 2 · Status ใส่เฉพาะ Pass/Fail/Blocked ที่ AI มั่นใจ ช่องว่าง = ให้คนตัดสินหรือทำเอง · ภาพหลักฐาน: .scratch/uat-prep/runner/shots/
A4: Run Order | B4: Test Case ID | C4: Tester (impersonated) | D4: AI Status | E4: Remarks | F4: Evidence
A5: 1 | B5: UAT-01 | C5: Pornthip (impersonated) | D5: Pass | E5: ตรงกับ Expected ข้อ 1-9 ทุกข้อ · ข้อ 8 (กดลิงก์ออกจากระบบเพื่อยืนยันว่ากดได้) ไม่ได้กดใน pre-UAT เพราะจะทำให้ session ของการรันหลุด — ให้คนกดในรอบจริง | F5: shots/UAT-01_userbar.png
A6: 2 | B6: UAT-02 | C6: Pornthip (impersonated) | D6: Pass | E6: ตรง Expected ข้อ 1-6 ทุกข้อ · ข้อสังเกต (ไม่ใช่ defect): ตารางของ Solution Delivery ไม่ได้ว่างเปล่าอย่างที่ note ของเคสคาด — แสดงแถว GL ของ 10IT012000 พร้อมยอด SAP ใช้จริง แต่ชั้น Pending เป็น 0 ทั้งหมด เพราะแถวมาจากชั้น SAP ไม่ใช่ข้อมูลที่กรอก ควรแก้ note ของเคสให้ตรง | F6: shots/UAT-02_picker_open.png, shots/UAT-02_solution_delivery_selected.png, shots/UAT-02_back_to_DA.png
A7: 5 | B7: UAT-06 | C7: Pornthip (impersonated) | D7: Pass | E7: ผ่านข้อ 2-5 · ข้อ 1 (ต้องเห็น 2 ฝั่ง): เห็นฝั่งเดียว — ยืนยันจากโค้ด GridTable.tsx:1156 ว่าฝั่งที่ไม่มีแถวถูกซ่อนโดยตั้งใจ จึงไม่ใช่ defect แต่ Expected ข้อ 1 ควรเขียนเพิ่มว่า 'ฝั่งที่ไม่มีแถวจะไม่แสดง' · 10IT011300 ไม่ปรากฏเพราะยังไม่มีแถวใด ๆ (ทั้ง Pending และ SAP) — ตรงเงื่อนไข 'มีเฉพาะ' แต่ควรให้คนยืนยันว่าถูกต้องตามสิทธิ์จริง | F7: shots/UAT-06-08_grid_DA.png
A8: 6 | B8: UAT-07 | C8: Pornthip (impersonated) | D8: Pass | E8: ข้อ 1-3 ผ่าน · ข้อ 4 ตรวจไม่ได้ในฝ่ายนี้เพราะไม่มีแถว Approved-only เลย บันทึกว่า 'ไม่พบ' ตาม Expected ข้อ 5 ไม่ถือเป็น Fail · ถ้าต้องการพิสูจน์ข้อ 4 จริง ต้องใช้ฝ่ายที่มีข้อมูล board_budget ปี 2026 | F8: shots/UAT-06-08_grid_DA.png
A9: 7 | B9: UAT-08 | C9: Pornthip (impersonated) | D9: Pass | E9: ข้อ 1-3 ตรงตาม Expected ทุกตัวอักษร · ข้อ 4 เป็นความเห็นของคนว่าอ่านแล้วเข้าใจไหม — AI ไม่ตัดสินแทน ให้ผู้ทดสอบยืนยันแล้วเปลี่ยน Status เป็น Pass เอง · jakkaritw ตัดสิน 2026-09-09: อ่านเข้าใจ / ยอมรับได้ → Pass | F9: shots/UAT-06-08_grid_DA.png
A10: 8 | B10: UAT-09 | C10: Pornthip (impersonated) | D10: Pass | E10: ผ่านข้อ 1, 3, 4 · ข้อ 2 (ข้อความ 'กำลังบันทึก…' ขึ้นแล้วหายเอง) automation อ่านหน้าจอไม่ทันช่วงสั้น ๆ นั้น จึงยังไม่ได้ยืนยันด้วยตา — ให้ผู้ทดสอบสังเกตในรอบจริง · เบี่ยงเบนจาก step 1: เคสระบุให้ใช้ Cost Center 10IT011300 แต่ CC นั้นไม่มีแถวใดในตารางเลย (ยังไม่ได้เพิ่มรายการ) จึงใช้ 10IT013000 แทน — ควรแก้เคสให้เพิ่มแถวก่อน หรือระบุ 10IT013000 | F10: shots/UAT-09_after_reload.png
A11: 9 | B11: UAT-10 | C11: Pornthip (impersonated) | D11: Pass | E11: ผ่านข้อ 1-5 ทุกข้อ ผลบวกตรงเครื่องคิดเลข | F11: shots/UAT-10_totals.png
A12: 10 | B12: UAT-11 | C12: Pornthip (impersonated) | D12: Pass | E12: ข้อ 1-2 ตรง Expected · ข้อ 3 (อ่านแล้วเข้าใจไหม) เป็นความเห็นของคน — ให้ผู้ทดสอบยืนยันแล้วเปลี่ยนเป็น Pass เอง · jakkaritw ตัดสิน 2026-09-09: อ่านเข้าใจ / ยอมรับได้ → Pass | F12: shots/UAT-06-08_grid_DA.png
A13: 11 | B13: UAT-12 | C13: Pornthip (impersonated) | D13: Pass | E13: ผ่านครบทั้ง 6 บรรทัดและ Expected ข้อ 1-9 · ข้อความแจ้งเตือนขึ้นทุกบรรทัดที่มีการปัดค่า (1, 2, 3, 4) และเงียบในบรรทัด 5, 6 ตามที่ Expected ระบุ · การจับเวลา 6 วินาที: automation ตรวจที่ 7 วินาทีแล้วข้อความหายไปแล้ว ไม่ได้จับเวลาละเอียดกว่านั้น | F13: shots/UAT-12_line1_toast.png, shots/UAT-12_line3_cap.png, shots/UAT-12_line4_drift.png, shots/UAT-12_line6_negative.png
A14: 12 | B14: UAT-13 | C14: Pornthip (impersonated) | D14: Pass | E14: ผ่านทุกข้อ · Expected ข้อ 1 เดิมคาดว่าเห็นข้อความ 2 ช่องพร้อมกัน แต่ระบบแจ้งทีละช่อง (ช่องแรกที่ขาดก่อน) เหมือนฟอร์มย่อยทุกฟอร์ม — jakkaritw ตัดสิน 2026-09-09 ว่ายอมรับได้ แก้ Expected ข้อ 1 ให้ตรงระบบแล้ว · ข้อ 3 ส่วน 'อ่านเข้าใจไหม' เป็นความเห็นของคน | F14: shots/UAT-13_case1_empty.png, shots/UAT-13_case2_cc_only.png, shots/UAT-13_case3_duplicate.png
A15: 13 | B15: UAT-14 | C15: Pornthip (impersonated) | D15: Pass | E15: ผ่าน Expected ข้อ 1-3 · ข้อ 4-5 ไม่มีแถวเดิมให้ทดสอบ บันทึกตามข้อ 6 · การซ่อนเป็นกติกาที่ตั้งไว้ 2026-08-29 (Training & Seminar → Talent & Culture เท่านั้น) | F15: shots/UAT-14_gl_search_noCC.png, shots/UAT-14_gl_search_withCC.png
A16: 14 | B16: UAT-15 | C16: Waraporn (impersonated, admin จริง) | D16: Pass | E16: ผ่านทุกข้อ · ไม่กด Submit/บันทึกใด ๆ ระหว่างเปิดโหมด Admin · รอบก่อน Blocked เพราะเครื่องมือ AI ถูกกันไม่ให้กด toggle — รอบนี้กดได้ (ที่ยังถูกกันคือปุ่มดำเนินการแทนขั้นที่ 1 เท่านั้น ดู UAT-44) | F16: shots/UAT-15_admin_gl_5210100150.png, shots/UAT-15_admin_gl_6210100150.png
... A58: 54 | B58: UAT-05 | C58: Pornthip (impersonated) — AI เฝ้าจนหมดอายุ; login จริงโดย jakkaritw | D58: Pass | E58: ผ่านทุกข้อ (1-4 ตาม Expected) · ข้อสังเกตที่รับไว้แล้วใน UAT-04: ข้อความในกล่องบอก '14 ชั่วโมง' ตายตัว ทั้งที่รอบนี้หมดอายุจริงที่ ~1 ชั่วโมง · ข้อ 9 ในเครื่องผู้ทดสอบจริงอาจเห็นหน้ากรอกรหัสของ Microsoft แทน SSO อัตโนมัติ — ปลายทางเดียวกัน · ข้อ 11 (คืนอายุ session เป็น 14 ชั่วโมง) อยู่ใน tracker uat-post-run-reset | F58: shots/UAT-05_typed_200_no_blur.png, shots/UAT-05_dialog.png, shots/UAT-05_dialog_after_esc_click.png, shots/UAT-05_dialog_before_relogin_click.png, shots/UAT-05_after_relogin_same_dept_year.png, uat05_out.json (ไทม์ไลน์นาทีต่อนาที)
A60: สรุป
A61: Pass | B61: 53
A62: Human decides / not run | B62: 1
A63: ไม่ได้รันโดย AI (ไม่มีแถว) | B63: 0
A65: งานที่คนต้องทำต่อ
A66: UAT-49 | B66: เหลืออย่างเดียว: เปิดอีเมล 'ได้รับการอนุมัติ' (03:22) บนมือถือ 1 ครั้ง แล้วยืนยันว่าอักษรไทยไม่เพี้ยนและอยู่ Inbox ของพรทิพย์ — ข้ออื่นทั้งหมด AI ตรวจแล้วผ่าน
